verilog/IBex/ibex_compressed_decoder.v
module ibex_compressed_decoder (
	instr_i,
	instr_o,
	is_compressed_o,
	illegal_instr_o
);
	input wire [31:0] instr_i;
	output reg [31:0] instr_o;
	output wire is_compressed_o;
	output reg illegal_instr_o;
	`include "ibex_pkg.v"
	always @(*) begin
		illegal_instr_o = 1'b0;
		instr_o = 1'bX;
		case (instr_i[1:0])
			2'b00:
				case (instr_i[15:13])
					3'b000: begin
						instr_o = {2'b0, instr_i[10:7], instr_i[12:11], instr_i[5], instr_i[6], 2'b00, 5'h02, 3'b000, 2'b01, instr_i[4:2], OPCODE_OP_IMM};
						if ((instr_i[12:5] == 8'b0))
							illegal_instr_o = 1'b1;
					end
					3'b010: instr_o = {5'b0, instr_i[5], instr_i[12:10], instr_i[6], 2'b00, 2'b01, instr_i[9:7], 3'b010, 2'b01, instr_i[4:2], OPCODE_LOAD};
					3'b110: instr_o = {5'b0, instr_i[5], instr_i[12], 2'b01, instr_i[4:2], 2'b01, instr_i[9:7], 3'b010, instr_i[11:10], instr_i[6], 2'b00, OPCODE_STORE};
					default: illegal_instr_o = 1'b1;
				endcase
			2'b01:
				case (instr_i[15:13])
					3'b000: instr_o = {{6 {instr_i[12]}}, instr_i[12], instr_i[6:2], instr_i[11:7], 3'b0, instr_i[11:7], OPCODE_OP_IMM};
					3'b001, 3'b101: instr_o = {instr_i[12], instr_i[8], instr_i[10:9], instr_i[6], instr_i[7], instr_i[2], instr_i[11], instr_i[5:3], {9 {instr_i[12]}}, 4'b0, ~instr_i[15], OPCODE_JAL};
					3'b010: instr_o = {{6 {instr_i[12]}}, instr_i[12], instr_i[6:2], 5'b0, 3'b0, instr_i[11:7], OPCODE_OP_IMM};
					3'b011: begin
						instr_o = {{15 {instr_i[12]}}, instr_i[6:2], instr_i[11:7], OPCODE_LUI};
						if ((instr_i[11:7] == 5'h02))
							instr_o = {{3 {instr_i[12]}}, instr_i[4:3], instr_i[5], instr_i[2], instr_i[6], 4'b0, 5'h02, 3'b000, 5'h02, OPCODE_OP_IMM};
						if (({instr_i[12], instr_i[6:2]} == 6'b0))
							illegal_instr_o = 1'b1;
					end
					3'b100:
						case (instr_i[11:10])
							2'b00, 2'b01: begin
								instr_o = {1'b0, instr_i[10], 5'b0, instr_i[6:2], 2'b01, instr_i[9:7], 3'b101, 2'b01, instr_i[9:7], OPCODE_OP_IMM};
								if ((instr_i[12] == 1'b1))
									illegal_instr_o = 1'b1;
							end
							2'b10: instr_o = {{6 {instr_i[12]}}, instr_i[12], instr_i[6:2], 2'b01, instr_i[9:7], 3'b111, 2'b01, instr_i[9:7], OPCODE_OP_IMM};
							2'b11:
								case ({instr_i[12], instr_i[6:5]})
									3'b000: instr_o = {2'b01, 5'b0, 2'b01, instr_i[4:2], 2'b01, instr_i[9:7], 3'b000, 2'b01, instr_i[9:7], OPCODE_OP};
									3'b001: instr_o = {7'b0, 2'b01, instr_i[4:2], 2'b01, instr_i[9:7], 3'b100, 2'b01, instr_i[9:7], OPCODE_OP};
									3'b010: instr_o = {7'b0, 2'b01, instr_i[4:2], 2'b01, instr_i[9:7], 3'b110, 2'b01, instr_i[9:7], OPCODE_OP};
									3'b011: instr_o = {7'b0, 2'b01, instr_i[4:2], 2'b01, instr_i[9:7], 3'b111, 2'b01, instr_i[9:7], OPCODE_OP};
									3'b100, 3'b101, 3'b110, 3'b111: illegal_instr_o = 1'b1;
									default: illegal_instr_o = 1'bX;
								endcase
							default: illegal_instr_o = 1'bX;
						endcase
					3'b110, 3'b111: instr_o = {{4 {instr_i[12]}}, instr_i[6:5], instr_i[2], 5'b0, 2'b01, instr_i[9:7], 2'b00, instr_i[13], instr_i[11:10], instr_i[4:3], instr_i[12], OPCODE_BRANCH};
					default: illegal_instr_o = 1'bX;
				endcase
			2'b10:
				case (instr_i[15:13])
					3'b000: begin
						instr_o = {7'b0, instr_i[6:2], instr_i[11:7], 3'b001, instr_i[11:7], OPCODE_OP_IMM};
						if ((instr_i[12] == 1'b1))
							illegal_instr_o = 1'b1;
					end
					3'b010: begin
						instr_o = {4'b0, instr_i[3:2], instr_i[12], instr_i[6:4], 2'b00, 5'h02, 3'b010, instr_i[11:7], OPCODE_LOAD};
						if ((instr_i[11:7] == 5'b0))
							illegal_instr_o = 1'b1;
					end
					3'b100:
						if ((instr_i[12] == 1'b0)) begin
							if ((instr_i[6:2] != 5'b0))
								instr_o = {7'b0, instr_i[6:2], 5'b0, 3'b0, instr_i[11:7], OPCODE_OP};
							else begin
								instr_o = {12'b0, instr_i[11:7], 3'b0, 5'b0, OPCODE_JALR};
								if ((instr_i[11:7] == 5'b0))
									illegal_instr_o = 1'b1;
							end
						end
						else if ((instr_i[6:2] != 5'b0))
							instr_o = {7'b0, instr_i[6:2], instr_i[11:7], 3'b0, instr_i[11:7], OPCODE_OP};
						else if ((instr_i[11:7] == 5'b0))
							instr_o = 32'h00_10_00_73;
						else
							instr_o = {12'b0, instr_i[11:7], 3'b000, 5'b00001, OPCODE_JALR};
					3'b110: instr_o = {4'b0, instr_i[8:7], instr_i[12], instr_i[6:2], 5'h02, 3'b010, instr_i[11:9], 2'b00, OPCODE_STORE};
					3'b001, 3'b011, 3'b101, 3'b111: illegal_instr_o = 1'b1;
					default: illegal_instr_o = 1'bX;
				endcase
			default: instr_o = instr_i;
		endcase
	end
	assign is_compressed_o = (instr_i[1:0] != 2'b11);
endmodule

example/ibex_compressed_decoder/ibex_compressed_decoder_bench.v
`timescale 1ns/1ps

module ibex_compressed_decoder_bench();

reg DEFAULT_CLOCK;
reg DEFAULT_RESET;
reg [31:0] instr_i;

wire is_compressed_o;
wire [31:0] instr_o;
wire illegal_instr_o;

ibex_compressed_decoder ibex_compressed_decoder_ (
	.instr_i(instr_i),
	.is_compressed_o(is_compressed_o),
	.instr_o(instr_o),
	.illegal_instr_o(illegal_instr_o));

	initial begin
		$dumpfile("/home/debjit/Work/GoldMine/dev_static_miner_integ/RunTime/goldmine.out/ibex_compressed_decoder/ibex_compressed_decoder.vcd");
		$dumpvars(0, ibex_compressed_decoder_bench);
		DEFAULT_CLOCK = 1;
		DEFAULT_RESET = 1;
		#26;
		DEFAULT_RESET = 0;
		#50000 $finish;
	end

	always begin
		#25 DEFAULT_CLOCK = ~DEFAULT_CLOCK;
	end

	always begin
		#24;
		instr_i = $random;
		#26;
	end

endmodule

example/ibex_compressed_decoder/ibex_compressed_decoder.vcd
$date
	Wed Apr  1 03:04:16 2020
$end
$version
	Icarus Verilog
$end
$timescale
	1ps
$end
$scope module ibex_compressed_decoder_bench $end
$var wire 1 ! is_compressed_o $end
$var wire 32 " instr_o [31:0] $end
$var wire 1 # illegal_instr_o $end
$var reg 1 $ DEFAULT_CLOCK $end
$var reg 1 % DEFAULT_RESET $end
$var reg 32 & instr_i [31:0] $end
$scope module ibex_compressed_decoder_ $end
$var wire 32 ' instr_i [31:0] $end
$var wire 1 ! is_compressed_o $end
$var reg 1 # illegal_instr_o $end
$var reg 32 ( instr_o [31:0] $end
$upscope $end
$upscope $end
$enddefinitions $end
#0
$dumpvars
bx (
bx '
bx &
1%
1$
x#
bx "
x!
$end
#24000
b0x "
b0x (
1#
1!
b10010000101010011010100100100 &
b10010000101010011010100100100 '
#25000
0$
#26000
0%
#50000
1$
#74000
b11111110000000000000111010010011 "
b11111110000000000000111010010011 (
0#
b11000000100010010101111010000001 &
b11000000100010010101111010000001 '
#75000
0$
#100000
1$
#124000
b11110000000001100000010111100011 "
b11110000000001100000010111100011 (
b10000100100001001101011000001001 &
b10000100100001001101011000001001 '
#125000
0$
#150000
1$
#174000
b10110001111100000101011001100011 "
b10110001111100000101011001100011 (
0!
b10110001111100000101011001100011 &
b10110001111100000101011001100011 '
#175000
0$
#200000
1$
#224000
b11111111111111100011101100110111 "
b11111111111111100011101100110111 (
1!
b110101110010111101100001101 &
b110101110010111101100001101 '
#225000
0$
#250000
1$
#274000
b11111110001101011111010110010011 "
b11111110001101011111010110010011 (
b1000110110111111001100110001101 &
b1000110110111111001100110001101 '
#275000
0$
#300000
1$
#324000
b1000001100101000101010000010011 "
b1000001100101000101010000010011 (
b10110010110000101000010001100101 &
b10110010110000101000010001100101 '
#325000
0$
#350000
1$
#374000
b10010000010010001000000011 "
b10010000010010001000000011 (
b10001001001101110101001000010010 &
b10001001001101110101001000010010 '
#375000
0$
#400000
1$
#424000
b1110001000001100011 "
b1110001000001100011 (
b111100111110001100000001 &
b111100111110001100000001 '
#425000
0$
#450000
1$
#474000
b10000001010000110101100011 "
b10000001010000110101100011 (
b110110101111100110100001101 &
b110110101111100110100001101 '
#475000
0$
#500000
1$
#524000
1#
b0x "
b0x (
b111011001000111111000101110110 &
b111011001000111111000101110110 '
#525000
0$
#550000
1$
#574000
b110000001010000111101100011 "
b110000001010000111101100011 (
0#
b11110100011011100110100111101 &
b11110100011011100110100111101 '
#575000
0$
#600000
1$
#624000
b11111111101100000000011110010011 "
b11111111101100000000011110010011 (
b1110110110101000101011111101101 &
b1110110110101000101011111101101 '
#625000
0$
#650000
1$
#674000
1#
b0x "
b0x (
b1000110001011011111011110001100 &
b1000110001011011111011110001100 '
#675000
0$
#700000
1$
#724000
b1100000001011001101101100011 "
b1100000001011001101101100011 (
0#
b1111100111111011110100111111001 &
b1111100111111011110100111111001 '
#725000
0$
#750000
1$
#774000
1#
b0x "
b0x (
b11100011001101110010010011000110 &
b11100011001101110010010011000110 '
#775000
0$
#800000
1$
#824000
b1000001000101001101010010010011 "
b1000001000101001101010010010011 (
0#
b11100010111101111000010011000101 &
b11100010111101111000010011000101 '
#825000
0$
#850000
1$
#874000
b110101000010010001000100011 "
b110101000010010001000100011 (
b11010101000100111101001010101010 &
b11010101000100111101001010101010 '
#875000
0$
#900000
1$
#924000
b11111110000001111001010011100011 "
b11111110000001111001010011100011 (
b1110010101011111111011111100101 &
b1110010101011111111011111100101 '
#925000
0$
#950000
1$
#974000
b10111011110100100111001001110111 "
b10111011110100100111001001110111 (
0!
b10111011110100100111001001110111 &
b10111011110100100111001001110111 '
#975000
0$
#1000000
1$
#1024000
b10010000010010011000100011 "
b10010000010010011000100011 (
1!
b10001001001100101101011000010010 &
b10001001001100101101011000010010 '
#1025000
0$
#1050000
1$
#1074000
b1000111111011001101101110001111 "
b1000111111011001101101110001111 (
0!
b1000111111011001101101110001111 &
b1000111111011001101101110001111 '
#1075000
0$
#1100000
1$
#1124000
1#
b0x "
b0x (
1!
b1111001001100000110100111110010 &
b1111001001100000110100111110010 '
#1125000
0$
#1150000
1$
#1174000
b1001101101000011010110011 "
b1001101101000011010110011 (
0#
b11100111011101101001011011001110 &
b11100111011101101001011011001110 '
#1175000
0$
#1200000
1$
#1224000
1#
b0x "
b0x (
b11110100000000000111101011101000 &
b11110100000000000111101011101000 '
#1225000
0$
#1250000
1$
#1274000
b1000100000000111010010011 "
b1000100000000111010010011 (
0#
b11100010110010100100111011000101 &
b11100010110010100100111011000101 '
#1275000
0$
#1300000
1$
#1324000
b1010001010010011110000011 "
b1010001010010011110000011 (
b101110010110000100100101011100 &
b101110010110000100100101011100 '
#1325000
0$
#1350000
1$
#1374000
b111111000000000000011101111 "
b111111000000000000011101111 (
b11011110100011100010100010111101 &
b11011110100011100010100010111101 '
#1375000
0$
#1400000
1$
#1424000
b11111110101100000000100000010011 "
b11111110101100000000100000010011 (
b10010110101010110101100000101101 &
b10010110101010110101100000101101 '
#1425000
0$
#1450000
1$
#1474000
b111010100000000000000011101111 "
b111010100000000000000011101111 (
b10110010101001110010011001100101 &
b10110010101001110010011001100101 '
#1475000
0$
#1500000
1$
#1524000
b10110001111011110110001001100011 "
b10110001111011110110001001100011 (
0!
b10110001111011110110001001100011 &
b10110001111011110110001001100011 '
#1525000
0$
#1550000
1$
#1574000
b1000000000011100110011 "
b1000000000011100110011 (
1!
b101011100111000011100001010 &
b101011100111000011100001010 '
#1575000
0$
#1600000
1$
#1624000
1#
b0x "
b0x (
b11000000001110110010001010000000 &
b11000000001110110010001010000000 '
#1625000
0$
#1650000
1$
#1674000
1#
b10000011001000010000100100000 &
b10000011001000010000100100000 '
#1675000
0$
#1700000
1$
#1724000
b1000100000010010010110000011 "
b1000100000010010010110000011 (
0#
b1010101011110000100010110101010 &
b1010101011110000100010110101010 '
#1725000
0$
#1750000
1$
#1774000
b10000001001000111101100011 "
b10000001001000111101100011 (
b11001110110011001100110010011101 &
b11001110110011001100110010011101 '
#1775000
0$
#1800000
1$
#1824000
1#
b0x "
b0x (
b11001011001000000011111010010110 &
b11001011001000000011111010010110 '
#1825000
0$
#1850000
1$
#1874000
b10001001100000111011100000010011 "
b10001001100000111011100000010011 (
0#
0!
b10001001100000111011100000010011 &
b10001001100000111011100000010011 '
#1875000
0$
#1900000
1$
#1924000
b10000011001111111111000011101111 "
b10000011001111111111000011101111 (
1!
b10000110101111000011100000001101 &
b10000110101111000011100000001101 '
#1925000
0$
#1950000
1$
#1974000
b10101001101001111101011001010011 "
b10101001101001111101011001010011 (
0!
b10101001101001111101011001010011 &
b10101001101001111101011001010011 '
#1975000
0$
#2000000
1$
#2024000
b110101100111111101110101101011 "
b110101100111111101110101101011 (
b110101100111111101110101101011 &
b110101100111111101110101101011 '
#2025000
0$
#2050000
1$
#2074000
b11111010000000000000011101111 "
b11111010000000000000011101111 (
1!
b11101010101001100010101011010101 &
b11101010101001100010101011010101 '
#2075000
0$
#2100000
1$
#2124000
b10010101000000011 "
b10010101000000011 (
b10000001000101110100101000000010 &
b10000001000101110100101000000010 '
#2125000
0$
#2150000
1$
#2174000
1#
b0x "
b0x (
b11010111010101100011111010101110 &
b11010111010101100011111010101110 '
#2175000
0$
#2200000
1$
#2224000
b10000001010001101101100011 "
b10000001010001101101100011 (
0#
b1110111111111110100100011101 &
b1110111111111110100100011101 '
#2225000
0$
#2250000
1$
#2274000
b11100111110001010111001011001111 "
b11100111110001010111001011001111 (
0!
b11100111110001010111001011001111 &
b11100111110001010111001011001111 '
#2275000
0$
#2300000
1$
#2324000
b10001100001000100100100100011 "
b10001100001000100100100100011 (
b10001100001000100100100100011 &
b10001100001000100100100100011 '
#2325000
0$
#2350000
1$
#2374000
1#
b0x "
b0x (
1!
b101000010010110010100001010 &
b101000010010110010100001010 '
#2375000
0$
#2400000
1$
#2424000
b1001010101001101010010011 "
b1001010101001101010010011 (
0#
b11100101011100110000101011001010 &
b11100101011100110000101011001010 '
#2425000
0$
#2450000
1$
#2474000
b101100001000010011110000011 "
b101100001000010011110000011 (
b10011110001100010100110000111100 &
b10011110001100010100110000111100 '
#2475000
0$
#2500000
1$
#2524000
1#
b0x "
b0x (
b1111001011010001011110111110010 &
b1111001011010001011110111110010 '
#2525000
0$
#2550000
1$
#2574000
1#
b1000101001011100110000110001010 &
b1000101001011100110000110001010 '
#2575000
0$
#2600000
1$
#2624000
b11011000000111111111000001101111 "
b11011000000111111111000001101111 (
0#
b100000110001001011001101000001 &
b100000110001001011001101000001 '
#2625000
0$
#2650000
1$
#2674000
1#
b0x "
b0x (
b11101100010010110011010011011000 &
b11101100010010110011010011011000 '
#2675000
0$
#2700000
1$
#2724000
1#
b111100001000001111001101111000 &
b111100001000001111001101111000 '
#2725000
0$
#2750000
1$
#2774000
b11111110001000101000001010010011 "
b11111110001000101000001010010011 (
0#
b11000100100010100001001010001001 &
b11000100100010100001001010001001 '
#2775000
0$
#2800000
1$
#2824000
b1110101110001010000110111101011 "
b1110101110001010000110111101011 (
0!
b1110101110001010000110111101011 &
b1110101110001010000110111101011 '
#2825000
0$
#2850000
1$
#2874000
1#
b0x "
b0x (
1!
b1011011000000100110010110110110 &
b1011011000000100110010110110110 '
#2875000
0$
#2900000
1$
#2924000
1#
b1100011010010111111100111000110 &
b1100011010010111111100111000110 '
#2925000
0$
#2950000
1$
#2974000
b101100111001001110010011 "
b101100111001001110010011 (
1#
b1010111000101010001001110101110 &
b1010111000101010001001110101110 '
#2975000
0$
#3000000
1$
#3024000
b10100100000010000011110010011 "
b10100100000010000011110010011 (
0#
b11011110011101010000001010111100 &
b11011110011101010000001010111100 '
#3025000
0$
#3050000
1$
#3074000
b1010101000010010110000100011 "
b1010101000010010110000100011 (
b10101000011111101110100101010 &
b10101000011111101110100101010 '
#3075000
0$
#3100000
1$
#3124000
b10000101110101111001101000001011 "
b10000101110101111001101000001011 (
0!
b10000101110101111001101000001011 &
b10000101110101111001101000001011 '
#3125000
0$
#3150000
1$
#3174000
b10111001110111111111000001101111 "
b10111001110111111111000001101111 (
1!
b10111000100101111011111001110001 &
b10111000100101111011111001110001 '
#3175000
0$
#3200000
1$
#3224000
b100000000000110010011 "
b100000000000110010011 (
b1000010111100100100000110000101 &
b1000010111100100100000110000101 '
#3225000
0$
#3250000
1$
#3274000
b100111111100100101010101001111 "
b100111111100100101010101001111 (
0!
b100111111100100101010101001111 &
b100111111100100101010101001111 '
#3275000
0$
#3300000
1$
#3324000
b10011101110011000110000000111011 "
b10011101110011000110000000111011 (
b10011101110011000110000000111011 &
b10011101110011000110000000111011 '
#3325000
0$
#3350000
1$
#3374000
1#
b0x "
b0x (
1!
b11101000001100011001100111010 &
b11101000001100011001100111010 '
#3375000
0$
#3400000
1$
#3424000
1#
b10111111001000110011001001111110 &
b10111111001000110011001001111110 '
#3425000
0$
#3450000
1$
#3474000
b10100000000101100010011 "
b10100000000101100010011 (
0#
b1010101010100100101100010101 &
b1010101010100100101100010101 '
#3475000
0$
#3500000
1$
#3524000
b11111111110001111111011110010011 "
b11111111110001111111011110010011 (
b1111000110110011001101111110001 &
b1111000110110011001101111110001 '
#3525000
0$
#3550000
1$
#3574000
b1011000000000101110010011 "
b1011000000000101110010011 (
b1101100100111000100101111011001 &
b1101100100111000100101111011001 '
#3575000
0$
#3600000
1$
#3624000
b1100001110001011100010011 "
b1100001110001011100010011 (
b110001001000110000011101100010 &
b110001001000110000011101100010 '
#3625000
0$
#3650000
1$
#3674000
1#
b0x "
b0x (
b100110001101011111101101001100 &
b100110001101011111101101001100 '
#3675000
0$
#3700000
1$
#3724000
b1001111101000010101010110011111 "
b1001111101000010101010110011111 (
0#
0!
b1001111101000010101010110011111 &
b1001111101000010101010110011111 '
#3725000
0$
#3750000
1$
#3774000
b1000111101110011010000110001111 "
b1000111101110011010000110001111 (
b1000111101110011010000110001111 &
b1000111101110011010000110001111 '
#3775000
0$
#3800000
1$
#3824000
1#
b0x "
b0x (
1!
b1111100011011011010100111111000 &
b1111100011011011010100111111000 '
#3825000
0$
#3850000
1$
#3874000
b11011011110011010110000010110111 "
b11011011110011010110000010110111 (
0#
0!
b11011011110011010110000010110111 &
b11011011110011010110000010110111 '
#3875000
0$
#3900000
1$
#3924000
b11001111110001000101011010011111 "
b11001111110001000101011010011111 (
b11001111110001000101011010011111 &
b11001111110001000101011010011111 '
#3925000
0$
#3950000
1$
#3974000
1#
b0x "
b0x (
1!
b10101110011111011001010001011100 &
b10101110011111011001010001011100 '
#3975000
0$
#4000000
1$
#4024000
b10101101110010111100000001011011 "
b10101101110010111100000001011011 (
0#
0!
b10101101110010111100000001011011 &
b10101101110010111100000001011011 '
#4025000
0$
#4050000
1$
#4074000
b11110100001111111111000011101111 "
b11110100001111111111000011101111 (
1!
b1000100110111100011011110001001 &
b1000100110111100011011110001001 '
#4075000
0$
#4100000
1$
#4124000
b10011000001111111111000011101111 "
b10011000001111111111000011101111 (
b10100100101011100011001001001001 &
b10100100101011100011001001001001 '
#4125000
0$
#4150000
1$
#4174000
1#
b0x "
b0x (
b11101000001000110011111011010000 &
b11101000001000110011111011010000 '
#4175000
0$
#4200000
1$
#4224000
b11101011111111101100000011010111 "
b11101011111111101100000011010111 (
0#
0!
b11101011111111101100000011010111 &
b11101011111111101100000011010111 '
#4225000
0$
#4250000
1$
#4274000
b11111000000001000001111011100011 "
b11111000000001000001111011100011 (
1!
b10101000110001111111110001010001 &
b10101000110001111111110001010001 '
#4275000
0$
#4300000
1$
#4324000
1#
b0x "
b0x (
b1001011001000010010111110010110 &
b1001011001000010010111110010110 '
#4325000
0$
#4350000
1$
#4374000
1#
b110000111010111111100001100 &
b110000111010111111100001100 '
#4375000
0$
#4400000
1$
#4424000
b101000000010010111000100011 "
b101000000010010111000100011 (
0#
b11100001001011001100111011000010 &
b11100001001011001100111011000010 '
#4425000
0$
#4450000
1$
#4474000
1#
b0x "
b0x (
b1100100010101111110110111001000 &
b1100100010101111110110111001000 '
#4475000
0$
#4500000
1$
#4524000
b10111011100000100101101001110111 "
b10111011100000100101101001110111 (
0#
0!
b10111011100000100101101001110111 &
b10111011100000100101101001110111 '
#4525000
0$
#4550000
1$
#4574000
b110000001010001111101100011 "
b110000001010001111101100011 (
1!
b11110111100101110110100111101 &
b11110111100101110110100111101 '
#4575000
0$
#4600000
1$
#4624000
b1010010000010010101000100011 "
b1010010000010010101000100011 (
b1001000011001101101100010010 &
b1001000011001101101100010010 '
#4625000
0$
#4650000
1$
#4674000
b1111100000001000000010011 "
b1111100000001000000010011 (
b10111111000001010000000001111110 &
b10111111000001010000000001111110 '
#4675000
0$
#4700000
1$
#4724000
b1101101010101010100010011 "
b1101101010101010100010011 (
b110110111001011000000101101101 &
b110110111001011000000101101101 '
#4725000
0$
#4750000
1$
#4774000
b100000001110001011101100011 "
b100000001110001011101100011 (
b11100110110011110011100111001 &
b11100110110011110011100111001 '
#4775000
0$
#4800000
1$
#4824000
b1111110100101000111100011111 "
b1111110100101000111100011111 (
0!
b1111110100101000111100011111 &
b1111110100101000111100011111 '
#4825000
0$
#4850000
1$
#4874000
b11101001111010111111011011010011 "
b11101001111010111111011011010011 (
b11101001111010111111011011010011 &
b11101001111010111111011011010011 '
#4875000
0$
#4900000
1$
#4924000
b1110111000000000000000011101111 "
b1110111000000000000000011101111 (
1!
b1000010110110010010111110000101 &
b1000010110110010010111110000101 '
#4925000
0$
#4950000
1$
#4974000
1#
b0x "
b0x (
b10111100000101001000100001111000 &
b10111100000101001000100001111000 '
#4975000
0$
#5000000
1$
#5024000
b101101110110100101100101011011 "
b101101110110100101100101011011 (
0#
0!
b101101110110100101100101011011 &
b101101110110100101100101011011 '
#5025000
0$
#5050000
1$
#5074000
b1001000000000101100010011 "
b1001000000000101100010011 (
1!
b100100100010110100101101001001 &
b100100100010110100101101001001 '
#5075000
0$
#5100000
1$
#5124000
b10011111111100101010111000111111 "
b10011111111100101010111000111111 (
0!
b10011111111100101010111000111111 &
b10011111111100101010111000111111 '
#5125000
0$
#5150000
1$
#5174000
1#
b0x "
b0x (
1!
b10101000011001010111100101010 &
b10101000011001010111100101010 '
#5175000
0$
#5200000
1$
#5224000
1#
b101100000101010110001101011000 &
b101100000101010110001101011000 '
#5225000
0$
#5250000
1$
#5274000
1#
b11000011001111110011100010000110 &
b11000011001111110011100010000110 '
#5275000
0$
#5300000
1$
#5324000
b1111001001110010010011 "
b1111001001110010010011 (
0#
b11000111000110100000110010001110 &
b11000111000110100000110010001110 '
#5325000
0$
#5350000
1$
#5374000
1#
b0x "
b0x (
b11001110001011111111001010011100 &
b11001110001011111111001010011100 '
#5375000
0$
#5400000
1$
#5424000
b1111010011000100110110011 "
b1111010011000100110110011 (
0#
b1111101001101011001100111111010 &
b1111101001101011001100111111010 '
#5425000
0$
#5450000
1$
#5474000
1#
b0x "
b0x (
b10010011011111011011110000100110 &
b10010011011111011011110000100110 '
#5475000
0$
#5500000
1$
#5524000
b111001100101100001011101110011 "
b111001100101100001011101110011 (
0#
0!
b111001100101100001011101110011 &
b111001100101100001011101110011 '
#5525000
0$
#5550000
1$
#5574000
b11010001100010111011010010100011 "
b11010001100010111011010010100011 (
b11010001100010111011010010100011 &
b11010001100010111011010010100011 '
#5575000
0$
#5600000
1$
#5624000
b10010111100110011010100000101111 "
b10010111100110011010100000101111 (
b10010111100110011010100000101111 &
b10010111100110011010100000101111 '
#5625000
0$
#5650000
1$
#5674000
b11011001110100101001001010110011 "
b11011001110100101001001010110011 (
b11011001110100101001001010110011 &
b11011001110100101001001010110011 '
#5675000
0$
#5700000
1$
#5724000
b10101111110110000101011001011111 "
b10101111110110000101011001011111 (
b10101111110110000101011001011111 &
b10101111110110000101011001011111 '
#5725000
0$
#5750000
1$
#5774000
b101001010000010000010010010011 "
b101001010000010000010010010011 (
1!
b100010001010010000110101000100 &
b100010001010010000110101000100 '
#5775000
0$
#5800000
1$
#5824000
b1111011111110001111110111110111 "
b1111011111110001111110111110111 (
0!
b1111011111110001111110111110111 &
b1111011111110001111110111110111 '
#5825000
0$
#5850000
1$
#5874000
b11100101100110110011011011001011 "
b11100101100110110011011011001011 (
b11100101100110110011011011001011 &
b11100101100110110011011011001011 '
#5875000
0$
#5900000
1$
#5924000
1#
b1100110101001101010010011 "
b1100110101001101010010011 (
1!
b11110011000010010001101011100110 &
b11110011000010010001101011100110 '
#5925000
0$
#5950000
1$
#5974000
b1011011000010010101000100011 "
b1011011000010010101000100011 (
0#
b101101001010001101101101011010 &
b101101001010001101101101011010 '
#5975000
0$
#6000000
1$
#6024000
b100000001010000000101100011 "
b100000001010000000101100011 (
b10100110011111100000100101001 &
b10100110011111100000100101001 '
#6025000
0$
#6050000
1$
#6074000
b1110000001101001000101100011 "
b1110000001101001000101100011 (
b11110110100000101110001011101101 &
b11110110100000101110001011101101 '
#6075000
0$
#6100000
1$
#6124000
1#
b0x "
b0x (
b11101101010100110110110011011010 &
b11101101010100110110110011011010 '
#6125000
0$
#6150000
1$
#6174000
b10111010100111111111000001101111 "
b10111010100111111111000001101111 (
0#
b10110010100111111011011001100101 &
b10110010100111111011011001100101 '
#6175000
0$
#6200000
1$
#6224000
b110000001101001001001100011 "
b110000001101001001001100011 (
b11011010100010101110001010110101 &
b11011010100010101110001010110101 '
#6225000
0$
#6250000
1$
#6274000
b11101111101111101001010011011111 "
b11101111101111101001010011011111 (
0!
b11101111101111101001010011011111 &
b11101111101111101001010011011111 '
#6275000
0$
#6300000
1$
#6324000
b11111111111010010000100100010011 "
b11111111111010010000100100010011 (
1!
b111100111100010001100101111001 &
b111100111100010001100101111001 '
#6325000
0$
#6350000
1$
#6374000
1#
b0x "
b0x (
b100010001100011111111101000100 &
b100010001100011111111101000100 '
#6375000
0$
#6400000
1$
#6424000
b100101010000010000011000010011 "
b100101010000010000011000010011 (
0#
b11101000011101000000110011010000 &
b11101000011101000000110011010000 '
#6425000
0$
#6450000
1$
#6474000
b101010110001101100010011 "
b101010110001101100010011 (
b10101000010010000101100101010 &
b10101000010010000101100101010 '
#6475000
0$
#6500000
1$
#6524000
b1010101111101101010110110101011 "
b1010101111101101010110110101011 (
0!
b1010101111101101010110110101011 &
b1010101111101101010110110101011 '
#6525000
0$
#6550000
1$
#6574000
b1000001100010010111000100011 "
b1000001100010010111000100011 (
1!
b111011011111100111100001110 &
b111011011111100111100001110 '
#6575000
0$
#6600000
1$
#6624000
1#
b0x "
b0x (
b1101110010111011010110111011100 &
b1101110010111011010110111011100 '
#6625000
0$
#6650000
1$
#6674000
1#
b11001101010111101011110010011010 &
b11001101010111101011110010011010 '
#6675000
0$
#6700000
1$
#6724000
b11111111111111111111001010110111 "
b11111111111111111111001010110111 (
0#
b11111110110111110111001011111101 &
b11111110110111110111001011111101 '
#6725000
0$
#6750000
1$
#6774000
b11100001111100010000001011000011 "
b11100001111100010000001011000011 (
0!
b11100001111100010000001011000011 &
b11100001111100010000001011000011 '
#6775000
0$
#6800000
1$
#6824000
1#
b0x "
b0x (
1!
b101011000011101110110101010110 &
b101011000011101110110101010110 '
#6825000
0$
#6850000
1$
#6874000
1#
b100111011110011110100101001110 &
b100111011110011110100101001110 '
#6875000
0$
#6900000
1$
#6924000
b10110011110110010111011001100111 "
b10110011110110010111011001100111 (
0#
0!
b10110011110110010111011001100111 &
b10110011110110010111011001100111 '
#6925000
0$
#6950000
1$
#6974000
1#
b0x "
b0x (
1!
b10000101001100010011010000001010 &
b10000101001100010011010000001010 '
#6975000
0$
#7000000
1$
#7024000
1#
b1011011011011111011100110110110 &
b1011011011011111011100110110110 '
#7025000
0$
#7050000
1$
#7074000
1#
b10011100000011101000101000111000 &
b10011100000011101000101000111000 '
#7075000
0$
#7100000
1$
#7124000
b1000001111001110101011100010011 "
b1000001111001110101011100010011 (
0#
b111100110100011000011101111001 &
b111100110100011000011101111001 '
#7125000
0$
#7150000
1$
#7174000
b100111001001010010000100011 "
b100111001001010010000100011 (
b11011100001010111100010010111000 &
b11011100001010111100010010111000 '
#7175000
0$
#7200000
1$
#7224000
1#
b0x "
b0x (
b1001010011101001011111110010100 &
b1001010011101001011111110010100 '
#7225000
0$
#7250000
1$
#7274000
b1001001110001100101110110010011 "
b1001001110001100101110110010011 (
0#
0!
b1001001110001100101110110010011 &
b1001001110001100101110110010011 '
#7275000
0$
#7300000
1$
#7324000
1#
b0x "
b0x (
1!
b10000010001111110010110000000100 &
b10000010001111110010110000000100 '
#7325000
0$
#7350000
1$
#7374000
b1000000001100000101101100011 "
b1000000001100000101101100011 (
0#
b10101100101101111100101001011001 &
b10101100101101111100101001011001 '
#7375000
0$
#7400000
1$
#7424000
b1101101110010110110100111011011 "
b1101101110010110110100111011011 (
0!
b1101101110010110110100111011011 &
b1101101110010110110100111011011 '
#7425000
0$
#7450000
1$
#7474000
b11111010000001100000110111100011 "
b11111010000001100000110111100011 (
1!
b10100110111111001101111001001101 &
b10100110111111001101111001001101 '
#7475000
0$
#7500000
1$
#7524000
b11111100011111111111000001101111 "
b11111100011111111111000001101111 (
b1101100101100001011011111011001 &
b1101100101100001011011111011001 '
#7525000
0$
#7550000
1$
#7574000
b111010101000000000000011101111 "
b111010101000000000000011101111 (
b10110110101001000010011001101101 &
b10110110101001000010011001101101 '
#7575000
0$
#7600000
1$
