verilog/IBex/ibex_controller.v
module ibex_controller (
	clk_i,
	rst_ni,
	fetch_enable_i,
	ctrl_busy_o,
	illegal_insn_i,
	ecall_insn_i,
	mret_insn_i,
	dret_insn_i,
	wfi_insn_i,
	ebrk_insn_i,
	csr_pipe_flush_i,
	instr_valid_i,
	instr_i,
	instr_compressed_i,
	instr_is_compressed_i,
	instr_fetch_err_i,
	pc_id_i,
	instr_valid_clear_o,
	id_in_ready_o,
	instr_req_o,
	pc_set_o,
	pc_mux_o,
	exc_pc_mux_o,
	exc_cause_o,
	lsu_addr_last_i,
	load_err_i,
	store_err_i,
	branch_set_i,
	jump_set_i,
	csr_mstatus_mie_i,
	csr_msip_i,
	csr_mtip_i,
	csr_meip_i,
	csr_mfip_i,
	irq_pending_i,
	irq_nm_i,
	debug_req_i,
	debug_cause_o,
	debug_csr_save_o,
	debug_mode_o,
	debug_single_step_i,
	debug_ebreakm_i,
	debug_ebreaku_i,
	csr_save_if_o,
	csr_save_id_o,
	csr_restore_mret_id_o,
	csr_restore_dret_id_o,
	csr_save_cause_o,
	csr_mtval_o,
	priv_mode_i,
	csr_mstatus_tw_i,
	stall_lsu_i,
	stall_multdiv_i,
	stall_jump_i,
	stall_branch_i,
	perf_jump_o,
	perf_tbranch_o
);
	localparam [3:0] RESET = 0;
	localparam [3:0] BOOT_SET = 1;
	localparam [3:0] WAIT_SLEEP = 2;
	localparam [3:0] SLEEP = 3;
	localparam [3:0] FIRST_FETCH = 4;
	localparam [3:0] DECODE = 5;
	localparam [3:0] FLUSH = 6;
	localparam [3:0] IRQ_TAKEN = 7;
	localparam [3:0] DBG_TAKEN_IF = 8;
	localparam [3:0] DBG_TAKEN_ID = 9;
	input wire clk_i;
	input wire rst_ni;
	input wire fetch_enable_i;
	output reg ctrl_busy_o;
	input wire illegal_insn_i;
	input wire ecall_insn_i;
	input wire mret_insn_i;
	input wire dret_insn_i;
	input wire wfi_insn_i;
	input wire ebrk_insn_i;
	input wire csr_pipe_flush_i;
	input wire instr_valid_i;
	input wire [31:0] instr_i;
	input wire [15:0] instr_compressed_i;
	input wire instr_is_compressed_i;
	input wire instr_fetch_err_i;
	input wire [31:0] pc_id_i;
	output wire instr_valid_clear_o;
	output wire id_in_ready_o;
	output reg instr_req_o;
	output reg pc_set_o;
	output reg [2:0] pc_mux_o;
	output reg [1:0] exc_pc_mux_o;
	output reg [5:0] exc_cause_o;
	input wire [31:0] lsu_addr_last_i;
	input wire load_err_i;
	input wire store_err_i;
	input wire branch_set_i;
	input wire jump_set_i;
	input wire csr_mstatus_mie_i;
	input wire csr_msip_i;
	input wire csr_mtip_i;
	input wire csr_meip_i;
	input wire [14:0] csr_mfip_i;
	input wire irq_pending_i;
	input wire irq_nm_i;
	input wire debug_req_i;
	output reg [2:0] debug_cause_o;
	output reg debug_csr_save_o;
	output wire debug_mode_o;
	input wire debug_single_step_i;
	input wire debug_ebreakm_i;
	input wire debug_ebreaku_i;
	output reg csr_save_if_o;
	output reg csr_save_id_o;
	output reg csr_restore_mret_id_o;
	output reg csr_restore_dret_id_o;
	output reg csr_save_cause_o;
	output reg [31:0] csr_mtval_o;
	input wire [1:0] priv_mode_i;
	input wire csr_mstatus_tw_i;
	input wire stall_lsu_i;
	input wire stall_multdiv_i;
	input wire stall_jump_i;
	input wire stall_branch_i;
	output reg perf_jump_o;
	output reg perf_tbranch_o;
	`include "ibex_pkg.v"
	reg [3:0] ctrl_fsm_cs;
	reg [3:0] ctrl_fsm_ns;
	reg nmi_mode_q;
	reg nmi_mode_d;
	reg debug_mode_q;
	reg debug_mode_d;
	reg load_err_q;
	wire load_err_d;
	reg store_err_q;
	wire store_err_d;
	reg exc_req_q;
	wire exc_req_d;
	reg illegal_insn_q;
	wire illegal_insn_d;
	wire stall;
	reg halt_if;
	reg flush_id;
	wire illegal_dret;
	wire illegal_umode;
	wire exc_req_lsu;
	wire special_req;
	wire enter_debug_mode;
	wire ebreak_into_debug;
	wire handle_irq;
	reg [3:0] mfip_id;
	wire unused_csr_mtip;
	wire ecall_insn;
	wire mret_insn;
	wire dret_insn;
	wire wfi_insn;
	wire ebrk_insn;
	wire csr_pipe_flush;
	wire instr_fetch_err;
	/* 
	NO $display allowed in Verilog code that will go thorugh GM static
	analysis
	always @(negedge clk_i)
		if (((((ctrl_fsm_cs == DECODE) && instr_valid_i) && !instr_fetch_err_i) && illegal_insn_d))
			$display("%t: Illegal instruction (hart %0x) at PC 0x%h: 0x%h", $time, ibex_core.hart_id_i, ibex_id_stage.pc_id_i, ibex_id_stage.instr_rdata_i);
	*/
	assign load_err_d = load_err_i;
	assign store_err_d = store_err_i;
	assign ecall_insn = (ecall_insn_i & instr_valid_i);
	assign mret_insn = (mret_insn_i & instr_valid_i);
	assign dret_insn = (dret_insn_i & instr_valid_i);
	assign wfi_insn = (wfi_insn_i & instr_valid_i);
	assign ebrk_insn = (ebrk_insn_i & instr_valid_i);
	assign csr_pipe_flush = (csr_pipe_flush_i & instr_valid_i);
	assign instr_fetch_err = (instr_fetch_err_i & instr_valid_i);
	assign illegal_dret = (dret_insn & ~debug_mode_q);
	assign illegal_umode = ((priv_mode_i != PRIV_LVL_M) & (mret_insn | (csr_mstatus_tw_i & wfi_insn)));
	assign illegal_insn_d = (((illegal_insn_i | illegal_dret) | illegal_umode) & (ctrl_fsm_cs != FLUSH));
	assign exc_req_d = ((((ecall_insn | ebrk_insn) | illegal_insn_d) | instr_fetch_err) & (ctrl_fsm_cs != FLUSH));
	assign exc_req_lsu = (store_err_i | load_err_i);
	assign special_req = (((((mret_insn | dret_insn) | wfi_insn) | csr_pipe_flush) | exc_req_d) | exc_req_lsu);
	assign enter_debug_mode = ((debug_req_i | (debug_single_step_i & instr_valid_i)) & ~debug_mode_q);
	assign ebreak_into_debug = ((priv_mode_i == PRIV_LVL_M) ? debug_ebreakm_i : ((priv_mode_i == PRIV_LVL_U) ? debug_ebreaku_i : 1'b0));
	assign handle_irq = (~debug_mode_q & ((irq_nm_i & ~nmi_mode_q) | (irq_pending_i & csr_mstatus_mie_i)));
	always @(*) begin : gen_mfip_id
		if (csr_mfip_i[14])
			mfip_id = 4'd14;
		else if (csr_mfip_i[13])
			mfip_id = 4'd13;
		else if (csr_mfip_i[12])
			mfip_id = 4'd12;
		else if (csr_mfip_i[11])
			mfip_id = 4'd11;
		else if (csr_mfip_i[10])
			mfip_id = 4'd10;
		else if (csr_mfip_i[9])
			mfip_id = 4'd9;
		else if (csr_mfip_i[8])
			mfip_id = 4'd8;
		else if (csr_mfip_i[7])
			mfip_id = 4'd7;
		else if (csr_mfip_i[6])
			mfip_id = 4'd6;
		else if (csr_mfip_i[5])
			mfip_id = 4'd5;
		else if (csr_mfip_i[5])
			mfip_id = 4'd5;
		else if (csr_mfip_i[4])
			mfip_id = 4'd4;
		else if (csr_mfip_i[3])
			mfip_id = 4'd3;
		else if (csr_mfip_i[2])
			mfip_id = 4'd2;
		else if (csr_mfip_i[1])
			mfip_id = 4'd1;
		else
			mfip_id = 4'd0;
	end
	assign unused_csr_mtip = csr_mtip_i;
	always @(*) begin
		instr_req_o = 1'b1;
		csr_save_if_o = 1'b0;
		csr_save_id_o = 1'b0;
		csr_restore_mret_id_o = 1'b0;
		csr_restore_dret_id_o = 1'b0;
		csr_save_cause_o = 1'b0;
		csr_mtval_o = 1'sb0;
		pc_mux_o = PC_BOOT;
		pc_set_o = 1'b0;
		exc_pc_mux_o = EXC_PC_IRQ;
		exc_cause_o = EXC_CAUSE_INSN_ADDR_MISA;
		ctrl_fsm_ns = ctrl_fsm_cs;
		ctrl_busy_o = 1'b1;
		halt_if = 1'b0;
		flush_id = 1'b0;
		debug_csr_save_o = 1'b0;
		debug_cause_o = DBG_CAUSE_EBREAK;
		debug_mode_d = debug_mode_q;
		nmi_mode_d = nmi_mode_q;
		perf_tbranch_o = 1'b0;
		perf_jump_o = 1'b0;
		case (ctrl_fsm_cs)
			RESET: begin
				instr_req_o = 1'b0;
				pc_mux_o = PC_BOOT;
				pc_set_o = 1'b1;
				if (fetch_enable_i)
					ctrl_fsm_ns = BOOT_SET;
			end
			BOOT_SET: begin
				instr_req_o = 1'b1;
				pc_mux_o = PC_BOOT;
				pc_set_o = 1'b1;
				ctrl_fsm_ns = FIRST_FETCH;
			end
			WAIT_SLEEP: begin
				ctrl_busy_o = 1'b0;
				instr_req_o = 1'b0;
				halt_if = 1'b1;
				flush_id = 1'b1;
				ctrl_fsm_ns = SLEEP;
			end
			SLEEP: begin
				instr_req_o = 1'b0;
				halt_if = 1'b1;
				flush_id = 1'b1;
				if (((((irq_nm_i || irq_pending_i) || debug_req_i) || debug_mode_q) || debug_single_step_i))
					ctrl_fsm_ns = FIRST_FETCH;
				else
					ctrl_busy_o = 1'b0;
			end
			FIRST_FETCH: begin
				if (id_in_ready_o)
					ctrl_fsm_ns = DECODE;
				if (handle_irq) begin
					ctrl_fsm_ns = IRQ_TAKEN;
					halt_if = 1'b1;
					flush_id = 1'b1;
				end
				if (enter_debug_mode) begin
					ctrl_fsm_ns = DBG_TAKEN_IF;
					halt_if = 1'b1;
				end
			end
			DECODE: begin
				if (instr_valid_i) begin
					if (special_req) begin
						ctrl_fsm_ns = FLUSH;
						halt_if = 1'b1;
					end
					else if ((branch_set_i || jump_set_i)) begin
						pc_mux_o = PC_JUMP;
						pc_set_o = 1'b1;
						perf_tbranch_o = branch_set_i;
						perf_jump_o = jump_set_i;
					end
					if (((enter_debug_mode || handle_irq) && stall))
						halt_if = 1'b1;
				end
				if ((!stall && !special_req))
					if (enter_debug_mode) begin
						ctrl_fsm_ns = DBG_TAKEN_IF;
						halt_if = 1'b1;
					end
					else if (handle_irq) begin
						ctrl_fsm_ns = IRQ_TAKEN;
						halt_if = 1'b1;
						flush_id = 1'b1;
					end
			end
			IRQ_TAKEN: begin
				if (handle_irq) begin
					pc_mux_o = PC_EXC;
					pc_set_o = 1'b1;
					exc_pc_mux_o = EXC_PC_IRQ;
					csr_save_if_o = 1'b1;
					csr_save_cause_o = 1'b1;
					if ((irq_nm_i && !nmi_mode_q)) begin
						exc_cause_o = EXC_CAUSE_IRQ_NM;
						nmi_mode_d = 1'b1;
					end
					else if ((csr_mfip_i != 15'b0))
						exc_cause_o = sv2v_cast_89EA8({2'b11, mfip_id});
					else if (csr_meip_i)
						exc_cause_o = EXC_CAUSE_IRQ_EXTERNAL_M;
					else if (csr_msip_i)
						exc_cause_o = EXC_CAUSE_IRQ_SOFTWARE_M;
					else
						exc_cause_o = EXC_CAUSE_IRQ_TIMER_M;
				end
				ctrl_fsm_ns = DECODE;
			end
			DBG_TAKEN_IF: begin
				if ((debug_single_step_i || debug_req_i)) begin
					flush_id = 1'b1;
					pc_mux_o = PC_EXC;
					pc_set_o = 1'b1;
					exc_pc_mux_o = EXC_PC_DBD;
					csr_save_if_o = 1'b1;
					debug_csr_save_o = 1'b1;
					csr_save_cause_o = 1'b1;
					if (debug_single_step_i)
						debug_cause_o = DBG_CAUSE_STEP;
					else
						debug_cause_o = DBG_CAUSE_HALTREQ;
					debug_mode_d = 1'b1;
				end
				ctrl_fsm_ns = DECODE;
			end
			DBG_TAKEN_ID: begin
				flush_id = 1'b1;
				pc_mux_o = PC_EXC;
				pc_set_o = 1'b1;
				exc_pc_mux_o = EXC_PC_DBD;
				if ((ebreak_into_debug && !debug_mode_q)) begin
					csr_save_cause_o = 1'b1;
					csr_save_id_o = 1'b1;
					debug_csr_save_o = 1'b1;
					debug_cause_o = DBG_CAUSE_EBREAK;
				end
				debug_mode_d = 1'b1;
				ctrl_fsm_ns = DECODE;
			end
			FLUSH: begin
				halt_if = 1'b1;
				flush_id = 1'b1;
				ctrl_fsm_ns = DECODE;
				if (((exc_req_q || store_err_q) || load_err_q)) begin
					pc_set_o = 1'b1;
					pc_mux_o = PC_EXC;
					exc_pc_mux_o = (debug_mode_q ? EXC_PC_DBG_EXC : EXC_PC_EXC);
					csr_save_id_o = 1'b1;
					csr_save_cause_o = 1'b1;
					if (instr_fetch_err) begin
						exc_cause_o = EXC_CAUSE_INSTR_ACCESS_FAULT;
						csr_mtval_o = pc_id_i;
					end
					else if (illegal_insn_q) begin
						exc_cause_o = EXC_CAUSE_ILLEGAL_INSN;
						csr_mtval_o = (instr_is_compressed_i ? {16'b0, instr_compressed_i} : instr_i);
					end
					else if (ecall_insn)
						exc_cause_o = ((priv_mode_i == PRIV_LVL_M) ? EXC_CAUSE_ECALL_MMODE : EXC_CAUSE_ECALL_UMODE);
					else if (ebrk_insn) begin
						if ((debug_mode_q | ebreak_into_debug)) begin
							pc_set_o = 1'b0;
							csr_save_id_o = 1'b0;
							csr_save_cause_o = 1'b0;
							ctrl_fsm_ns = DBG_TAKEN_ID;
							flush_id = 1'b0;
						end
						else
							exc_cause_o = EXC_CAUSE_BREAKPOINT;
					end
					else if (store_err_q) begin
						exc_cause_o = EXC_CAUSE_STORE_ACCESS_FAULT;
						csr_mtval_o = lsu_addr_last_i;
					end
					else begin
						exc_cause_o = EXC_CAUSE_LOAD_ACCESS_FAULT;
						csr_mtval_o = lsu_addr_last_i;
					end
				end
				else if (mret_insn) begin
					pc_mux_o = PC_ERET;
					pc_set_o = 1'b1;
					csr_restore_mret_id_o = 1'b1;
					if (nmi_mode_q)
						nmi_mode_d = 1'b0;
				end
				else if (dret_insn) begin
					pc_mux_o = PC_DRET;
					pc_set_o = 1'b1;
					debug_mode_d = 1'b0;
					csr_restore_dret_id_o = 1'b1;
				end
				else if (wfi_insn)
					ctrl_fsm_ns = WAIT_SLEEP;
				else if ((csr_pipe_flush && handle_irq))
					ctrl_fsm_ns = IRQ_TAKEN;
				if (enter_debug_mode)
					ctrl_fsm_ns = DBG_TAKEN_IF;
			end
			default: begin
			instr_req_o = 1'b0;
			ctrl_fsm_ns = 1'bX;
		end
		endcase
	end
	assign debug_mode_o = debug_mode_q;
	assign stall = (((stall_lsu_i | stall_multdiv_i) | stall_jump_i) | stall_branch_i);
	assign id_in_ready_o = (~stall & ~halt_if);
	assign instr_valid_clear_o = (~(stall | halt_if) | flush_id);
	always @(posedge clk_i or negedge rst_ni) begin : update_regs
		if (!rst_ni) begin
			ctrl_fsm_cs <= RESET;
			nmi_mode_q <= 1'b0;
			debug_mode_q <= 1'b0;
			load_err_q <= 1'b0;
			store_err_q <= 1'b0;
			exc_req_q <= 1'b0;
			illegal_insn_q <= 1'b0;
		end
		else begin
			ctrl_fsm_cs <= ctrl_fsm_ns;
			nmi_mode_q <= nmi_mode_d;
			debug_mode_q <= debug_mode_d;
			load_err_q <= load_err_d;
			store_err_q <= store_err_d;
			exc_req_q <= exc_req_d;
			illegal_insn_q <= illegal_insn_d;
		end
	end
	function [(6 - 1):0] sv2v_cast_89EA8;
		input [(6 - 1):0] inp;
		sv2v_cast_89EA8 = inp;
	endfunction
endmodule

example/ibex_controller/ibex_controller_bench.v
`timescale 1ns/1ps

module ibex_controller_bench();

reg irq_pending_i;
reg fetch_enable_i;
reg csr_mtip_i;
reg [31:0] lsu_addr_last_i;
reg stall_multdiv_i;
reg csr_pipe_flush_i;
reg csr_msip_i;
reg instr_valid_i;
reg dret_insn_i;
reg [31:0] pc_id_i;
reg stall_lsu_i;
reg ebrk_insn_i;
reg jump_set_i;
reg debug_single_step_i;
reg wfi_insn_i;
reg [15:0] instr_compressed_i;
reg instr_is_compressed_i;
reg csr_meip_i;
reg illegal_insn_i;
reg stall_jump_i;
reg instr_fetch_err_i;
reg rst_ni;
reg [31:0] instr_i;
reg irq_nm_i;
reg debug_ebreakm_i;
reg branch_set_i;
reg mret_insn_i;
reg stall_branch_i;
reg debug_ebreaku_i;
reg [1:0] priv_mode_i;
reg csr_mstatus_tw_i;
reg store_err_i;
reg clk_i;
reg ecall_insn_i;
reg csr_mstatus_mie_i;
reg [14:0] csr_mfip_i;
reg load_err_i;
reg debug_req_i;

wire id_in_ready_o;
wire pc_set_o;
wire instr_valid_clear_o;
wire csr_save_id_o;
wire [31:0] csr_mtval_o;
wire [2:0] debug_cause_o;
wire [5:0] exc_cause_o;
wire perf_jump_o;
wire csr_restore_mret_id_o;
wire perf_tbranch_o;
wire csr_save_if_o;
wire instr_req_o;
wire csr_restore_dret_id_o;
wire debug_csr_save_o;
wire [2:0] pc_mux_o;
wire debug_mode_o;
wire ctrl_busy_o;
wire csr_save_cause_o;
wire [1:0] exc_pc_mux_o;

ibex_controller ibex_controller_ (
	.irq_pending_i(irq_pending_i),
	.fetch_enable_i(fetch_enable_i),
	.csr_mtip_i(csr_mtip_i),
	.lsu_addr_last_i(lsu_addr_last_i),
	.stall_multdiv_i(stall_multdiv_i),
	.csr_pipe_flush_i(csr_pipe_flush_i),
	.csr_msip_i(csr_msip_i),
	.instr_valid_i(instr_valid_i),
	.dret_insn_i(dret_insn_i),
	.pc_id_i(pc_id_i),
	.stall_lsu_i(stall_lsu_i),
	.ebrk_insn_i(ebrk_insn_i),
	.jump_set_i(jump_set_i),
	.debug_single_step_i(debug_single_step_i),
	.wfi_insn_i(wfi_insn_i),
	.instr_compressed_i(instr_compressed_i),
	.instr_is_compressed_i(instr_is_compressed_i),
	.csr_meip_i(csr_meip_i),
	.illegal_insn_i(illegal_insn_i),
	.stall_jump_i(stall_jump_i),
	.instr_fetch_err_i(instr_fetch_err_i),
	.rst_ni(rst_ni),
	.instr_i(instr_i),
	.irq_nm_i(irq_nm_i),
	.debug_ebreakm_i(debug_ebreakm_i),
	.branch_set_i(branch_set_i),
	.mret_insn_i(mret_insn_i),
	.stall_branch_i(stall_branch_i),
	.debug_ebreaku_i(debug_ebreaku_i),
	.priv_mode_i(priv_mode_i),
	.csr_mstatus_tw_i(csr_mstatus_tw_i),
	.store_err_i(store_err_i),
	.clk_i(clk_i),
	.ecall_insn_i(ecall_insn_i),
	.csr_mstatus_mie_i(csr_mstatus_mie_i),
	.csr_mfip_i(csr_mfip_i),
	.load_err_i(load_err_i),
	.debug_req_i(debug_req_i),
	.id_in_ready_o(id_in_ready_o),
	.pc_set_o(pc_set_o),
	.instr_valid_clear_o(instr_valid_clear_o),
	.csr_save_id_o(csr_save_id_o),
	.csr_mtval_o(csr_mtval_o),
	.debug_cause_o(debug_cause_o),
	.exc_cause_o(exc_cause_o),
	.perf_jump_o(perf_jump_o),
	.csr_restore_mret_id_o(csr_restore_mret_id_o),
	.perf_tbranch_o(perf_tbranch_o),
	.csr_save_if_o(csr_save_if_o),
	.instr_req_o(instr_req_o),
	.csr_restore_dret_id_o(csr_restore_dret_id_o),
	.debug_csr_save_o(debug_csr_save_o),
	.pc_mux_o(pc_mux_o),
	.debug_mode_o(debug_mode_o),
	.ctrl_busy_o(ctrl_busy_o),
	.csr_save_cause_o(csr_save_cause_o),
	.exc_pc_mux_o(exc_pc_mux_o));

	initial begin
		$dumpfile("/scratch/users/dp638/Work/Important/gm_static_miner_integ/RunTime/goldmine.out/ibex_controller/ibex_controller.vcd");
		$dumpvars(0, ibex_controller_bench.ibex_controller_);
		clk_i = 1;
		rst_ni = 0;
		#26;
		rst_ni = 1;
		#500000 $finish;
	end

	always begin
		#25 clk_i = ~clk_i;
	end

	always begin
		#24;
		irq_pending_i = $random;
		fetch_enable_i = $random;
		csr_mtip_i = $random;
		lsu_addr_last_i = $random;
		stall_multdiv_i = $random;
		csr_pipe_flush_i = $random;
		csr_msip_i = $random;
		instr_valid_i = $random;
		dret_insn_i = $random;
		pc_id_i = $random;
		stall_lsu_i = $random;
		ebrk_insn_i = $random;
		jump_set_i = $random;
		debug_single_step_i = $random;
		wfi_insn_i = $random;
		instr_compressed_i = $random;
		instr_is_compressed_i = $random;
		csr_meip_i = $random;
		illegal_insn_i = $random;
		stall_jump_i = $random;
		instr_fetch_err_i = $random;
		instr_i = $random;
		irq_nm_i = $random;
		debug_ebreakm_i = $random;
		branch_set_i = $random;
		mret_insn_i = $random;
		stall_branch_i = $random;
		debug_ebreaku_i = $random;
		priv_mode_i = $random;
		csr_mstatus_tw_i = $random;
		store_err_i = $random;
		ecall_insn_i = $random;
		csr_mstatus_mie_i = $random;
		csr_mfip_i = $random;
		load_err_i = $random;
		debug_req_i = $random;
		#26;
	end

endmodule

example/ibex_controller/ibex_controller.vcd
$date
	Sat Mar 14 21:25:42 2020
$end
$version
	Icarus Verilog
$end
$timescale
	1ps
$end
$scope module ibex_controller_bench $end
$scope module ibex_controller_ $end
$var wire 1 ! branch_set_i $end
$var wire 1 " clk_i $end
$var wire 1 # csr_meip_i $end
$var wire 15 $ csr_mfip_i [14:0] $end
$var wire 1 % csr_msip_i $end
$var wire 1 & csr_mstatus_mie_i $end
$var wire 1 ' csr_mstatus_tw_i $end
$var wire 1 ( csr_mtip_i $end
$var wire 1 ) csr_pipe_flush $end
$var wire 1 * csr_pipe_flush_i $end
$var wire 1 + debug_ebreakm_i $end
$var wire 1 , debug_ebreaku_i $end
$var wire 1 - debug_mode_o $end
$var wire 1 . debug_req_i $end
$var wire 1 / debug_single_step_i $end
$var wire 1 0 dret_insn $end
$var wire 1 1 dret_insn_i $end
$var wire 1 2 ebrk_insn $end
$var wire 1 3 ebrk_insn_i $end
$var wire 1 4 ecall_insn $end
$var wire 1 5 ecall_insn_i $end
$var wire 1 6 enter_debug_mode $end
$var wire 1 7 exc_req_d $end
$var wire 1 8 exc_req_lsu $end
$var wire 1 9 fetch_enable_i $end
$var wire 1 : handle_irq $end
$var wire 1 ; id_in_ready_o $end
$var wire 1 < illegal_dret $end
$var wire 1 = illegal_insn_d $end
$var wire 1 > illegal_insn_i $end
$var wire 1 ? illegal_umode $end
$var wire 16 @ instr_compressed_i [15:0] $end
$var wire 1 A instr_fetch_err $end
$var wire 1 B instr_fetch_err_i $end
$var wire 32 C instr_i [31:0] $end
$var wire 1 D instr_is_compressed_i $end
$var wire 1 E instr_valid_clear_o $end
$var wire 1 F instr_valid_i $end
$var wire 1 G irq_nm_i $end
$var wire 1 H irq_pending_i $end
$var wire 1 I jump_set_i $end
$var wire 1 J load_err_d $end
$var wire 1 K load_err_i $end
$var wire 32 L lsu_addr_last_i [31:0] $end
$var wire 1 M mret_insn $end
$var wire 1 N mret_insn_i $end
$var wire 32 O pc_id_i [31:0] $end
$var wire 2 P priv_mode_i [1:0] $end
$var wire 1 Q rst_ni $end
$var wire 1 R special_req $end
$var wire 1 S stall $end
$var wire 1 T stall_branch_i $end
$var wire 1 U stall_jump_i $end
$var wire 1 V stall_lsu_i $end
$var wire 1 W stall_multdiv_i $end
$var wire 1 X store_err_d $end
$var wire 1 Y store_err_i $end
$var wire 1 Z unused_csr_mtip $end
$var wire 1 [ wfi_insn $end
$var wire 1 \ wfi_insn_i $end
$var wire 1 ] ebreak_into_debug $end
$var reg 32 ^ csr_mtval_o [31:0] $end
$var reg 1 _ csr_restore_dret_id_o $end
$var reg 1 ` csr_restore_mret_id_o $end
$var reg 1 a csr_save_cause_o $end
$var reg 1 b csr_save_id_o $end
$var reg 1 c csr_save_if_o $end
$var reg 1 d ctrl_busy_o $end
$var reg 4 e ctrl_fsm_cs [3:0] $end
$var reg 4 f ctrl_fsm_ns [3:0] $end
$var reg 3 g debug_cause_o [2:0] $end
$var reg 1 h debug_csr_save_o $end
$var reg 1 i debug_mode_d $end
$var reg 1 j debug_mode_q $end
$var reg 6 k exc_cause_o [5:0] $end
$var reg 2 l exc_pc_mux_o [1:0] $end
$var reg 1 m exc_req_q $end
$var reg 1 n flush_id $end
$var reg 1 o halt_if $end
$var reg 1 p illegal_insn_q $end
$var reg 1 q instr_req_o $end
$var reg 1 r load_err_q $end
$var reg 4 s mfip_id [3:0] $end
$var reg 1 t nmi_mode_d $end
$var reg 1 u nmi_mode_q $end
$var reg 3 v pc_mux_o [2:0] $end
$var reg 1 w pc_set_o $end
$var reg 1 x perf_jump_o $end
$var reg 1 y perf_tbranch_o $end
$var reg 1 z store_err_q $end
$scope function sv2v_cast_89EA8 $end
$var reg 6 { inp [5:0] $end
$var reg 6 | sv2v_cast_89EA8 [5:0] $end
$upscope $end
$scope begin gen_mfip_id $end
$upscope $end
$scope begin update_regs $end
$upscope $end
$upscope $end
$upscope $end
$enddefinitions $end
#0
$dumpvars
bx |
bx {
0z
0y
0x
1w
b0 v
0u
0t
bx s
0r
0q
0p
0o
0n
0m
b1 l
b0 k
0j
0i
0h
b1 g
b0 f
b0 e
1d
0c
0b
0a
0`
0_
b0 ^
x]
x\
x[
xZ
xY
xX
xW
xV
xU
xT
xS
xR
0Q
bx P
bx O
xN
xM
bx L
xK
xJ
xI
xH
xG
xF
xE
xD
bx C
xB
xA
bx @
x?
x>
x=
x<
x;
x:
x9
x8
x7
x6
x5
x4
x3
x2
x1
x0
x/
x.
0-
x,
x+
x*
x)
x(
x'
x&
x%
bx $
x#
1"
x!
$end
#24000
17
0E
0;
1=
0?
0:
16
1R
0]
0<
b1101 s
18
1S
04
0M
00
0[
02
0A
0)
b1 f
1w
0q
1.
0J
0K
b10000100100000 $
0&
05
1X
1Y
1'
b1 P
1,
0T
1N
0!
0+
0G
b1000111111011001101101110001111 C
0B
1U
1>
0#
1D
b10010011000110 @
1\
0/
1I
13
0V
b110110101111100110100001101 O
11
0F
1%
1*
1W
b10110001111100000101011001100011 L
1Z
1(
19
0H
#25000
0"
#26000
1Q
#50000
b100 f
1w
1q
1p
1m
1z
b1 e
1"
#74000
07
0=
b1110 s
b100 f
1w
1J
1K
b100101100010101 $
1T
0N
b1011011000000100110010110110110 C
1B
0>
b110000110001010 @
0\
0I
03
1V
b11100111110001010111001011001111 O
0%
b10101001101001111101011001010011 L
#75000
0"
#100000
1o
b1000 f
0w
0p
0m
1r
b100 e
1"
#124000
17
1E
1n
1:
1=
06
b1101 s
1]
1o
b111 f
0.
0J
0K
b11100010000110 $
b11 P
0,
1N
1!
1+
1G
b10111111000001010000000001111110 C
0B
1>
0D
b111111100001100 @
1/
1I
b1000100110111100011011110001001 O
1%
0W
b1000111101110011010000110001111 L
09
#125000
0"
#150000
0E
b101 f
1t
b111111 k
1a
1c
1w
b10 v
0n
0o
1p
1m
0r
b111 e
1"
#174000
b1011 s
0]
1t
b101 f
b111111 k
1w
b10 v
1a
1c
1J
1K
b101000111000 $
0'
b10 P
1,
0N
0!
0+
b10101000010010000101100101010 C
0U
1#
1D
b1011011001100101 @
0V
b11100101100110110011011011001011 O
1W
b11010001100010111011010010100011 L
#175000
0"
#200000
0:
b0 k
0w
b0 v
0a
0c
1r
1u
b101 e
1"
#224000
1=
1?
b1100 s
08
1M
1[
12
1)
1A
1o
b110 f
0J
0K
b1100110111010 $
1&
0X
0Y
1'
0,
0T
1N
1!
0G
b10010111010111001001110000101110 C
1B
1U
0>
0#
0D
b11101101001 @
1\
0/
0I
13
b1100101001110110100100111001010 O
01
1F
b10101100101101111100101001011001 L
0Z
0(
19
#225000
0"
#250000
1E
b1100101001110110100100111001010 ^
b1 k
1a
1b
b0 l
b10 v
1w
b101 f
1n
1o
0=
07
0z
0r
b110 e
1"
#274000
16
18
b111 s
0?
1]
0M
0[
02
0A
0)
1n
1o
b1000 f
b10 k
b0 l
1w
b10 v
b10101000011000111001011001010000 ^
1a
1b
1.
1J
1K
b10101000 $
0&
b11 P
1T
1+
1G
b10101000011000111001011001010000 C
0B
1>
1#
b10101101111001 @
1/
03
b1101110010111110000111111011100 O
11
0F
0%
0*
0W
b11011100001110110000100110111 L
1Z
1(
09
1H
#275000
0"
#300000
17
b101 f
1i
b100 g
1h
1c
1n
0o
b0 k
b10 l
1w
b10 v
b0 ^
1a
0b
1=
0p
0m
1r
b1000 e
1"
#324000
07
1;
0=
b1100 s
0S
0]
1i
b100 g
1h
1n
b101 f
b10 l
1w
b10 v
1a
1c
b1111000001011 $
1&
1X
1Y
b10 P
0T
0!
0+
0G
b11000011001100111001000010000110 C
1B
0U
0>
b1001110110111010 @
0\
1I
13
b1100100011001001110001111001000 O
1*
b10101001011111011010100101010 L
0H
#325000
0"
#350000
06
b1 g
0h
0n
b1 l
0w
b0 v
0a
0c
1z
1-
1j
b101 e
1"
#374000
17
0E
0;
1=
b1011 s
1S
0.
b111100101011 $
15
0'
1T
0N
1+
b101001111011111110100101010011 C
0B
1U
1>
0#
1D
b1001110100011000 @
0I
03
1V
b10010110100001001110000000101101 O
01
1%
0*
b110101110011011011111101101011 L
19
#375000
0"
#400000
1p
1m
1"
#424000
b1101 s
08
1]
0J
0K
b10101001101111 $
0&
05
0X
0Y
b11 P
1,
0T
1!
1G
b1101101111001011011101111011011 C
1B
1#
0D
b10001000100111 @
1\
1I
13
b11011000101011001110001010110001 O
0%
b10000010001000100011101000000100 L
1H
#425000
0"
#450000
0z
0r
1"
#474000
b1100 s
0]
14
1M
1[
1A
1o
b110 f
b1001010100000 $
15
0,
1T
1N
0!
0+
b10101101011001111110001001011010 C
0#
1D
b1110111001000011 @
03
0V
b11110000111001000011100111100 O
1F
1W
b1111011000011011010100111110110 L
0Z
0(
09
0H
#475000
0"
#500000
1E
b11110000111001000011100111100 ^
b1 k
1a
1b
b11 l
b10 v
1w
b101 f
1n
1o
0=
07
b110 e
1"
#524000
0?
0M
0A
0[
12
10
1)
1n
1o
b101 f
b10 k
b11 l
1w
b10 v
b100011011010101111110101000110 ^
1a
1b
b1111000100101 $
b0 P
0T
0N
1!
0G
b100011011010101111110101000110 C
0B
0U
0D
b111100011101101 @
0\
0I
13
1V
b1110001110000010010100111100011 O
11
1%
1*
0W
b10111100110011000100001001111001 L
1Z
1(
19
1H
#525000
0"
#550000
0E
b110 f
0n
1o
b0 k
b1 l
0w
b0 v
b0 ^
0a
0b
1=
17
0p
0m
b101 e
1"
