example/ibex_multdiv_slow/preprocessed_code/ibex_multdiv_slow_preprocessed_code.v
module ibex_multdiv_slow (
	clk_i,
	rst_ni,
	mult_en_i,
	div_en_i,
	operator_i,
	signed_mode_i,
	op_a_i,
	op_b_i,
	alu_adder_ext_i,
	alu_adder_i,
	equal_to_zero,
	alu_operand_a_o,
	alu_operand_b_o,
	multdiv_result_o,
	valid_o
);
	localparam [2:0] MD_IDLE = 0;
	localparam [2:0] MD_ABS_A = 1;
	localparam [2:0] MD_ABS_B = 2;
	localparam [2:0] MD_COMP = 3;
	localparam [2:0] MD_LAST = 4;
	localparam [2:0] MD_CHANGE_SIGN = 5;
	localparam [2:0] MD_FINISH = 6;
	input wire clk_i;
	input wire rst_ni;
	input wire mult_en_i;
	input wire div_en_i;
	input wire [1:0] operator_i;
	input wire [1:0] signed_mode_i;
	input wire [31:0] op_a_i;
	input wire [31:0] op_b_i;
	input wire [33:0] alu_adder_ext_i;
	input wire [31:0] alu_adder_i;
	input wire equal_to_zero;
	output reg [32:0] alu_operand_a_o;
	output reg [32:0] alu_operand_b_o;
	output reg [31:0] multdiv_result_o;
	output wire valid_o;
localparam   OPCODE_LOAD     = 7'h03;
localparam   OPCODE_MISC_MEM = 7'h0f;
localparam   OPCODE_OP_IMM   = 7'h13;
localparam   OPCODE_AUIPC    = 7'h17;
localparam   OPCODE_STORE    = 7'h23;
localparam   OPCODE_OP       = 7'h33;
localparam   OPCODE_LUI      = 7'h37;
localparam   OPCODE_BRANCH   = 7'h63;
localparam   OPCODE_JALR     = 7'h67;
localparam   OPCODE_JAL      = 7'h6f;
localparam   OPCODE_SYSTEM   = 7'h73;


////////////////////
// ALU operations //
////////////////////

  // Arithmetics
localparam   ALU_ADD = 5'h0;
localparam   ALU_SUB = 5'h1;

  // Logics
localparam   ALU_XOR = 5'h2;
localparam   ALU_OR = 5'h3;
localparam   ALU_AND = 5'h4;

  // Shifts
localparam   ALU_SRA = 5'h5;
localparam   ALU_SRL = 5'h6;
localparam   ALU_SLL = 5'h7;

  // Comparisons
localparam   ALU_LT = 5'h8;
localparam   ALU_LTU = 5'h9;
localparam   ALU_GE = 5'ha;
localparam   ALU_GEU = 5'hb;
localparam   ALU_EQ = 5'hc;
localparam   ALU_NE = 5'hd;

  // Set lower than
localparam   ALU_SLT = 5'he;
localparam   ALU_SLTU = 5'hf;

  // Multiplier/divider
localparam   MD_OP_MULL = 2'h0;
localparam   MD_OP_MULH = 2'h1;
localparam   MD_OP_DIV = 2'h2;
localparam   MD_OP_REM = 2'h3;


//////////////////////////////////
// Control and status registers //
//////////////////////////////////

// CSR operations
localparam   CSR_OP_READ = 2'h0;
localparam   CSR_OP_WRITE = 2'h1;
localparam   CSR_OP_SET = 2'h2;
localparam   CSR_OP_CLEAR = 2'h3;


// Privileged mode
localparam   PRIV_LVL_M = 2'b11;
localparam   PRIV_LVL_H = 2'b10;
localparam   PRIV_LVL_S = 2'b01;
localparam   PRIV_LVL_U = 2'b00;

// Constants for the dcsr.xdebugver fields
localparam    XDEBUGVER_NO     = 4'd0; // no external debug support
localparam    XDEBUGVER_STD    = 4'd4; // external debug according to RISC-V debug spec
localparam    XDEBUGVER_NONSTD = 4'd15; // debug not conforming to RISC-V debug spec


//////////////
// ID stage //
//////////////

// Operand a selection
localparam   OP_A_REG_A = 2'h0;
localparam   OP_A_FWD = 2'h1;
localparam   OP_A_CURRPC = 2'h2;
localparam   OP_A_IMM = 2'h3;

// Immediate a selection
localparam   IMM_A_Z = 1'b0;
localparam   IMM_A_ZERO = 1'b1;

// Operand b selection
localparam   OP_B_REG_B = 1'b0;
localparam   OP_B_IMM = 1'b1;

// Immediate b selection
localparam   IMM_B_I = 3'h0;
localparam   IMM_B_S = 3'h1;
localparam   IMM_B_B = 3'h2;
localparam   IMM_B_U = 3'h3;
localparam   IMM_B_J = 3'h4;
localparam   IMM_B_INCR_PC = 3'h4;
localparam   IMM_B_INCR_ADDR = 3'h5;

// Regfile write data selection
localparam   RF_WD_LSU = 2'h0;
localparam   RF_WD_EX = 2'h1;
localparam   RF_WD_CSR = 2'h2;

//////////////
// IF stage //
//////////////

// PC mux selection
localparam   PC_BOOT = 3'h0;
localparam   PC_JUMP = 3'h1;
localparam   PC_EXC = 3'h2;
localparam   PC_ERET = 3'h3;
localparam   PC_DRET = 3'h4;

// Exception PC mux selection
localparam   EXC_PC_EXC = 2'h0;
localparam   EXC_PC_IRQ = 2'h1;
localparam   EXC_PC_DBD = 2'h2;
localparam   EXC_PC_DBG_EXC = 2'h3; // Exception while in debug mode

// Exception cause
localparam   EXC_CAUSE_IRQ_SOFTWARE_M     = {1'b1, 5'd03};
localparam   EXC_CAUSE_IRQ_TIMER_M        = {1'b1, 5'd07};
localparam   EXC_CAUSE_IRQ_EXTERNAL_M     = {1'b1, 5'd11};
  // EXC_CAUSE_IRQ_FAST_0      = {1'b1, 5'd16};
  // EXC_CAUSE_IRQ_FAST_14     = {1'b1, 5'd30};
localparam   EXC_CAUSE_IRQ_NM             = {1'b1, 5'd31}; // == EXC_CAUSE_IRQ_FAST_15
localparam   EXC_CAUSE_INSN_ADDR_MISA     = {1'b0, 5'd00};
localparam   EXC_CAUSE_INSTR_ACCESS_FAULT = {1'b0, 5'd01};
localparam   EXC_CAUSE_ILLEGAL_INSN       = {1'b0, 5'd02};
localparam   EXC_CAUSE_BREAKPOINT         = {1'b0, 5'd03};
localparam   EXC_CAUSE_LOAD_ACCESS_FAULT  = {1'b0, 5'd05};
localparam   EXC_CAUSE_STORE_ACCESS_FAULT = {1'b0, 5'd07};
localparam   EXC_CAUSE_ECALL_UMODE        = {1'b0, 5'd08};
localparam   EXC_CAUSE_ECALL_MMODE        = {1'b0, 5'd11};

// Debug cause
localparam   DBG_CAUSE_NONE    = 3'h0;
localparam   DBG_CAUSE_EBREAK  = 3'h1;
localparam   DBG_CAUSE_TRIGGER = 3'h2;
localparam   DBG_CAUSE_HALTREQ = 3'h3;
localparam   DBG_CAUSE_STEP    = 3'h4;

// PMP constants
parameter   PMP_MAX_REGIONS      = 16;
parameter   PMP_CFG_W            = 8;

// PMP acces type
parameter   PMP_I = 0;
parameter   PMP_D = 1;

localparam   PMP_ACC_EXEC    = 2'b00;
localparam   PMP_ACC_WRITE   = 2'b01;
localparam   PMP_ACC_READ    = 2'b10;

// PMP cfg structures
localparam   PMP_MODE_OFF   = 2'b00;
localparam   PMP_MODE_TOR   = 2'b01;
localparam   PMP_MODE_NA4   = 2'b10;
localparam   PMP_MODE_NAPOT = 2'b11;

//typedef struct packed {
//  logic          lock;
//  pmp_cfg_mode_e mode;
//  logic          exec;
//  logic          write;
//  logic          read;

// CSRs
  // Machine information
localparam   CSR_MHARTID   = 12'hF14;

  // Machine trap setup
localparam   CSR_MSTATUS   = 12'h300;
localparam   CSR_MISA      = 12'h301;
localparam   CSR_MIE       = 12'h304;
localparam   CSR_MTVEC     = 12'h305;

  // Machine trap handling
localparam   CSR_MSCRATCH  = 12'h340;
localparam   CSR_MEPC      = 12'h341;
localparam   CSR_MCAUSE    = 12'h342;
localparam   CSR_MTVAL     = 12'h343;
localparam   CSR_MIP       = 12'h344;

  // Physical memory protection
localparam   CSR_PMPCFG0   = 12'h3A0;
localparam   CSR_PMPCFG1   = 12'h3A1;
localparam   CSR_PMPCFG2   = 12'h3A2;
localparam   CSR_PMPCFG3   = 12'h3A3;
localparam   CSR_PMPADDR0  = 12'h3B0;
localparam   CSR_PMPADDR1  = 12'h3B1;
localparam   CSR_PMPADDR2  = 12'h3B2;
localparam   CSR_PMPADDR3  = 12'h3B3;
localparam   CSR_PMPADDR4  = 12'h3B4;
localparam   CSR_PMPADDR5  = 12'h3B5;
localparam   CSR_PMPADDR6  = 12'h3B6;
localparam   CSR_PMPADDR7  = 12'h3B7;
localparam   CSR_PMPADDR8  = 12'h3B8;
localparam   CSR_PMPADDR9  = 12'h3B9;
localparam   CSR_PMPADDR10 = 12'h3BA;
localparam   CSR_PMPADDR11 = 12'h3BB;
localparam   CSR_PMPADDR12 = 12'h3BC;
localparam   CSR_PMPADDR13 = 12'h3BD;
localparam   CSR_PMPADDR14 = 12'h3BE;
localparam   CSR_PMPADDR15 = 12'h3BF;

  // Debug/trace
localparam   CSR_DCSR      = 12'h7b0;
localparam   CSR_DPC       = 12'h7b1;

  // Debug
localparam   CSR_DSCRATCH0 = 12'h7b2; // optional
localparam   CSR_DSCRATCH1 = 12'h7b3; // optional

  // Machine Counter/Timers
localparam   CSR_MCOUNTINHIBIT  = 12'h320;
localparam   CSR_MHPMEVENT3     = 12'h323;
localparam   CSR_MHPMEVENT4     = 12'h324;
localparam   CSR_MHPMEVENT5     = 12'h325;
localparam   CSR_MHPMEVENT6     = 12'h326;
localparam   CSR_MHPMEVENT7     = 12'h327;
localparam   CSR_MHPMEVENT8     = 12'h328;
localparam   CSR_MHPMEVENT9     = 12'h329;
localparam   CSR_MHPMEVENT10    = 12'h32A;
localparam   CSR_MHPMEVENT11    = 12'h32B;
localparam   CSR_MHPMEVENT12    = 12'h32C;
localparam   CSR_MHPMEVENT13    = 12'h32D;
localparam   CSR_MHPMEVENT14    = 12'h32E;
localparam   CSR_MHPMEVENT15    = 12'h32F;
localparam   CSR_MHPMEVENT16    = 12'h330;
localparam   CSR_MHPMEVENT17    = 12'h331;
localparam   CSR_MHPMEVENT18    = 12'h332;
localparam   CSR_MHPMEVENT19    = 12'h333;
localparam   CSR_MHPMEVENT20    = 12'h334;
localparam   CSR_MHPMEVENT21    = 12'h335;
localparam   CSR_MHPMEVENT22    = 12'h336;
localparam   CSR_MHPMEVENT23    = 12'h337;
localparam   CSR_MHPMEVENT24    = 12'h338;
localparam   CSR_MHPMEVENT25    = 12'h339;
localparam   CSR_MHPMEVENT26    = 12'h33A;
localparam   CSR_MHPMEVENT27    = 12'h33B;
localparam   CSR_MHPMEVENT28    = 12'h33C;
localparam   CSR_MHPMEVENT29    = 12'h33D;
localparam   CSR_MHPMEVENT30    = 12'h33E;
localparam   CSR_MHPMEVENT31    = 12'h33F;
localparam   CSR_MCYCLE         = 12'hB00;
localparam   CSR_MINSTRET       = 12'hB02;
localparam   CSR_MHPMCOUNTER3   = 12'hB03;
localparam   CSR_MHPMCOUNTER4   = 12'hB04;
localparam   CSR_MHPMCOUNTER5   = 12'hB05;
localparam   CSR_MHPMCOUNTER6   = 12'hB06;
localparam   CSR_MHPMCOUNTER7   = 12'hB07;
localparam   CSR_MHPMCOUNTER8   = 12'hB08;
localparam   CSR_MHPMCOUNTER9   = 12'hB09;
localparam   CSR_MHPMCOUNTER10  = 12'hB0A;
localparam   CSR_MHPMCOUNTER11  = 12'hB0B;
localparam   CSR_MHPMCOUNTER12  = 12'hB0C;
localparam   CSR_MHPMCOUNTER13  = 12'hB0D;
localparam   CSR_MHPMCOUNTER14  = 12'hB0E;
localparam   CSR_MHPMCOUNTER15  = 12'hB0F;
localparam   CSR_MHPMCOUNTER16  = 12'hB10;
localparam   CSR_MHPMCOUNTER17  = 12'hB11;
localparam   CSR_MHPMCOUNTER18  = 12'hB12;
localparam   CSR_MHPMCOUNTER19  = 12'hB13;
localparam   CSR_MHPMCOUNTER20  = 12'hB14;
localparam   CSR_MHPMCOUNTER21  = 12'hB15;
localparam   CSR_MHPMCOUNTER22  = 12'hB16;
localparam   CSR_MHPMCOUNTER23  = 12'hB17;
localparam   CSR_MHPMCOUNTER24  = 12'hB18;
localparam   CSR_MHPMCOUNTER25  = 12'hB19;
localparam   CSR_MHPMCOUNTER26  = 12'hB1A;
localparam   CSR_MHPMCOUNTER27  = 12'hB1B;
localparam   CSR_MHPMCOUNTER28  = 12'hB1C;
localparam   CSR_MHPMCOUNTER29  = 12'hB1D;
localparam   CSR_MHPMCOUNTER30  = 12'hB1E;
localparam   CSR_MHPMCOUNTER31  = 12'hB1F;
localparam   CSR_MCYCLEH        = 12'hB80;
localparam   CSR_MINSTRETH      = 12'hB82;
localparam   CSR_MHPMCOUNTER3H  = 12'hB83;
localparam   CSR_MHPMCOUNTER4H  = 12'hB84;
localparam   CSR_MHPMCOUNTER5H  = 12'hB85;
localparam   CSR_MHPMCOUNTER6H  = 12'hB86;
localparam   CSR_MHPMCOUNTER7H  = 12'hB87;
localparam   CSR_MHPMCOUNTER8H  = 12'hB88;
localparam   CSR_MHPMCOUNTER9H  = 12'hB89;
localparam   CSR_MHPMCOUNTER10H = 12'hB8A;
localparam   CSR_MHPMCOUNTER11H = 12'hB8B;
localparam   CSR_MHPMCOUNTER12H = 12'hB8C;
localparam   CSR_MHPMCOUNTER13H = 12'hB8D;
localparam   CSR_MHPMCOUNTER14H = 12'hB8E;
localparam   CSR_MHPMCOUNTER15H = 12'hB8F;
localparam   CSR_MHPMCOUNTER16H = 12'hB90;
localparam   CSR_MHPMCOUNTER17H = 12'hB91;
localparam   CSR_MHPMCOUNTER18H = 12'hB92;
localparam   CSR_MHPMCOUNTER19H = 12'hB93;
localparam   CSR_MHPMCOUNTER20H = 12'hB94;
localparam   CSR_MHPMCOUNTER21H = 12'hB95;
localparam   CSR_MHPMCOUNTER22H = 12'hB96;
localparam   CSR_MHPMCOUNTER23H = 12'hB97;
localparam   CSR_MHPMCOUNTER24H = 12'hB98;
localparam   CSR_MHPMCOUNTER25H = 12'hB99;
localparam   CSR_MHPMCOUNTER26H = 12'hB9A;
localparam   CSR_MHPMCOUNTER27H = 12'hB9B;
localparam   CSR_MHPMCOUNTER28H = 12'hB9C;
localparam   CSR_MHPMCOUNTER29H = 12'hB9D;
localparam   CSR_MHPMCOUNTER30H = 12'hB9E;
localparam   CSR_MHPMCOUNTER31H = 12'hB9F;

// CSR pmp-related offsets
parameter [11:0] CSR_OFF_PMP_CFG  = 12'h3A0; // pmp_cfg  @ 12'h3a0 - 12'h3a3
parameter [11:0] CSR_OFF_PMP_ADDR = 12'h3B0; // pmp_addr @ 12'h3b0 - 12'h3bf

// CSR status bits
parameter   CSR_MSTATUS_MIE_BIT      = 3;
parameter   CSR_MSTATUS_MPIE_BIT     = 7;
parameter   CSR_MSTATUS_MPP_BIT_LOW  = 11;
parameter   CSR_MSTATUS_MPP_BIT_HIGH = 12;
parameter   CSR_MSTATUS_MPRV_BIT     = 17;
parameter   CSR_MSTATUS_TW_BIT       = 21;

// CSR errupt pending/enable  int bits
parameter   CSR_MSIX_BIT      = 3;
parameter   CSR_MTIX_BIT      = 7;
parameter   CSR_MEIX_BIT      = 11;
parameter   CSR_MFIX_BIT_LOW  = 16;
parameter   CSR_MFIX_BIT_HIGH = 30;

	reg [4:0] multdiv_state_q;
	reg [4:0] multdiv_state_d;
	wire [4:0] multdiv_state_m1;
	reg [2:0] md_state_q;
	reg [2:0] md_state_d;
	reg [32:0] accum_window_q;
	reg [32:0] accum_window_d;
	wire [32:0] res_adder_l;
	wire [32:0] res_adder_h;
	reg [32:0] op_b_shift_q;
	reg [32:0] op_b_shift_d;
	reg [32:0] op_a_shift_q;
	reg [32:0] op_a_shift_d;
	wire [32:0] op_a_ext;
	wire [32:0] op_b_ext;
	wire [32:0] one_shift;
	wire [32:0] op_a_bw_pp;
	wire [32:0] op_a_bw_last_pp;
	wire [31:0] b_0;
	wire sign_a;
	wire sign_b;
	wire [32:0] next_reminder;
	wire [32:0] next_quotient;
	wire [32:0] op_remainder;
	reg [31:0] op_numerator_q;
	reg [31:0] op_numerator_d;
	wire is_greater_equal;
	wire div_change_sign;
	wire rem_change_sign;
	assign res_adder_l = alu_adder_ext_i[32:0];
	assign res_adder_h = alu_adder_ext_i[33:1];
	always @(*) begin
		alu_operand_a_o = accum_window_q;
		multdiv_result_o = (div_en_i ? accum_window_q[31:0] : res_adder_l);
		case (operator_i)
			MD_OP_MULL: alu_operand_b_o = op_a_bw_pp;
			MD_OP_MULH: alu_operand_b_o = ((md_state_q == MD_LAST) ? op_a_bw_last_pp : op_a_bw_pp);
			default: case (md_state_q)
			MD_IDLE: begin
				alu_operand_a_o = {32'h0, 1'b1};
				alu_operand_b_o = {~op_b_i, 1'b1};
			end
			MD_ABS_A: begin
				alu_operand_a_o = {32'h0, 1'b1};
				alu_operand_b_o = {~op_a_i, 1'b1};
			end
			MD_ABS_B: begin
				alu_operand_a_o = {32'h0, 1'b1};
				alu_operand_b_o = {~op_b_i, 1'b1};
			end
			MD_CHANGE_SIGN: begin
				alu_operand_a_o = {32'h0, 1'b1};
				alu_operand_b_o = {~accum_window_q[31:0], 1'b1};
			end
			default: begin
			alu_operand_a_o = {accum_window_q[31:0], 1'b1};
			alu_operand_b_o = {~op_b_shift_q[31:0], 1'b1};
		end
		endcase
		endcase
	end
	assign is_greater_equal = (((accum_window_q[31] ^ op_b_shift_q[31]) == 1'b0) ? (res_adder_h[31] == 1'b0) : accum_window_q[31]);
	assign one_shift = ({32'b0, 1'b1} << multdiv_state_q);
	assign next_reminder = (is_greater_equal ? res_adder_h : op_remainder);
	assign next_quotient = (is_greater_equal ? (op_a_shift_q | one_shift) : op_a_shift_q);
	assign b_0 = {32 {op_b_shift_q[0]}};
	assign op_a_bw_pp = {~(op_a_shift_q[32] & op_b_shift_q[0]), (op_a_shift_q[31:0] & b_0)};
	assign op_a_bw_last_pp = {(op_a_shift_q[32] & op_b_shift_q[0]), ~(op_a_shift_q[31:0] & b_0)};
	assign sign_a = (op_a_i[31] & signed_mode_i[0]);
	assign sign_b = (op_b_i[31] & signed_mode_i[1]);
	assign op_a_ext = {sign_a, op_a_i};
	assign op_b_ext = {sign_b, op_b_i};
	assign op_remainder = accum_window_q[32:0];
	assign multdiv_state_m1 = (multdiv_state_q - 5'h1);
	assign div_change_sign = (sign_a ^ sign_b);
	assign rem_change_sign = sign_a;
	always @(posedge clk_i or negedge rst_ni) begin : proc_multdiv_state_q
		if (!rst_ni) begin
			multdiv_state_q <= 5'h0;
			accum_window_q <= 33'h0;
			op_b_shift_q <= 33'h0;
			op_a_shift_q <= 33'h0;
			op_numerator_q <= 32'h0;
			md_state_q <= MD_IDLE;
		end
		else begin
			multdiv_state_q <= multdiv_state_d;
			accum_window_q <= accum_window_d;
			op_b_shift_q <= op_b_shift_d;
			op_a_shift_q <= op_a_shift_d;
			op_numerator_q <= op_numerator_d;
			md_state_q <= md_state_d;
		end
	end
	always @(*) begin
		multdiv_state_d = multdiv_state_q;
		accum_window_d = accum_window_q;
		op_b_shift_d = op_b_shift_q;
		op_a_shift_d = op_a_shift_q;
		op_numerator_d = op_numerator_q;
		md_state_d = md_state_q;
		if ((mult_en_i || div_en_i))
			case (md_state_q)
				MD_IDLE: begin
					case (operator_i)
						MD_OP_MULL: begin
							op_a_shift_d = (op_a_ext << 1);
							accum_window_d = {~(op_a_ext[32] & op_b_i[0]), (op_a_ext[31:0] & {32 {op_b_i[0]}})};
							op_b_shift_d = (op_b_ext >> 1);
							md_state_d = MD_COMP;
						end
						MD_OP_MULH: begin
							op_a_shift_d = op_a_ext;
							accum_window_d = {1'b1, ~(op_a_ext[32] & op_b_i[0]), (op_a_ext[31:1] & {31 {op_b_i[0]}})};
							op_b_shift_d = (op_b_ext >> 1);
							md_state_d = MD_COMP;
						end
						MD_OP_DIV: begin
							accum_window_d = {33 {1'b1}};
							md_state_d = (equal_to_zero ? MD_FINISH : MD_ABS_A);
						end
						default: begin
						accum_window_d = op_a_ext;
						md_state_d = (equal_to_zero ? MD_FINISH : MD_ABS_A);
					end
					endcase
					multdiv_state_d = 5'd31;
				end
				MD_ABS_A: begin
					op_a_shift_d = 1'sb0;
					op_numerator_d = (sign_a ? alu_adder_i : op_a_i);
					md_state_d = MD_ABS_B;
				end
				MD_ABS_B: begin
					accum_window_d = {32'h0, op_numerator_q[31]};
					op_b_shift_d = (sign_b ? alu_adder_i : op_b_i);
					md_state_d = MD_COMP;
				end
				MD_COMP: begin
					multdiv_state_d = multdiv_state_m1;
					case (operator_i)
						MD_OP_MULL: begin
							accum_window_d = res_adder_l;
							op_a_shift_d = (op_a_shift_q << 1);
							op_b_shift_d = (op_b_shift_q >> 1);
						end
						MD_OP_MULH: begin
							accum_window_d = res_adder_h;
							op_a_shift_d = op_a_shift_q;
							op_b_shift_d = (op_b_shift_q >> 1);
						end
						default: begin
						accum_window_d = {next_reminder[31:0], op_numerator_q[multdiv_state_m1]};
						op_a_shift_d = next_quotient;
					end
					endcase
					md_state_d = ((multdiv_state_q == 5'd1) ? MD_LAST : MD_COMP);
				end
				MD_LAST:
					case (operator_i)
						MD_OP_MULL: begin
							accum_window_d = res_adder_l;
							md_state_d = MD_IDLE;
						end
						MD_OP_MULH: begin
							accum_window_d = res_adder_l;
							md_state_d = MD_IDLE;
						end
						MD_OP_DIV: begin
							accum_window_d = next_quotient;
							md_state_d = MD_CHANGE_SIGN;
						end
						default: begin
						accum_window_d = {1'b0, next_reminder[31:0]};
						md_state_d = MD_CHANGE_SIGN;
					end
					endcase
				MD_CHANGE_SIGN: begin
					md_state_d = MD_FINISH;
					case (operator_i)
						MD_OP_DIV: accum_window_d = (div_change_sign ? alu_adder_i : accum_window_q);
						default: accum_window_d = (rem_change_sign ? alu_adder_i : accum_window_q);
					endcase
				end
				MD_FINISH: md_state_d = MD_IDLE;
				default: md_state_d = 1'bX;
			endcase
	end
	assign valid_o = ((md_state_q == MD_FINISH) | ((md_state_q == MD_LAST) & ((operator_i == MD_OP_MULL) | (operator_i == MD_OP_MULH))));
endmodule

example/ibex_multdiv_slow/ibex_multdiv_slow_bench.v
`timescale 1ns/1ps

module ibex_multdiv_slow_bench();

reg rst_ni;
reg [33:0] alu_adder_ext_i;
reg div_en_i;
reg [31:0] op_a_i;
reg [1:0] operator_i;
reg mult_en_i;
reg [1:0] signed_mode_i;
reg clk_i;
reg [31:0] alu_adder_i;
reg equal_to_zero;
reg [31:0] op_b_i;

wire valid_o;
wire [32:0] alu_operand_a_o;
wire [32:0] alu_operand_b_o;
wire [31:0] multdiv_result_o;

ibex_multdiv_slow ibex_multdiv_slow_ (
	.rst_ni(rst_ni),
	.alu_adder_ext_i(alu_adder_ext_i),
	.div_en_i(div_en_i),
	.op_a_i(op_a_i),
	.operator_i(operator_i),
	.mult_en_i(mult_en_i),
	.signed_mode_i(signed_mode_i),
	.clk_i(clk_i),
	.alu_adder_i(alu_adder_i),
	.equal_to_zero(equal_to_zero),
	.op_b_i(op_b_i),
	.valid_o(valid_o),
	.alu_operand_a_o(alu_operand_a_o),
	.alu_operand_b_o(alu_operand_b_o),
	.multdiv_result_o(multdiv_result_o));

	initial begin
		$dumpfile("/scratch/users/dp638/Work/Important/gm_static_miner_integ/RunTime/goldmine.out/ibex_multdiv_slow/ibex_multdiv_slow.vcd");
		$dumpvars(0, ibex_multdiv_slow_bench.ibex_multdiv_slow_);
		clk_i = 1;
		rst_ni = 0;
		#26;
		rst_ni = 1;
		#50000 $finish;
	end

	always begin
		#25 clk_i = ~clk_i;
	end

	always begin
		#24;
		alu_adder_ext_i = $random;
		div_en_i = $random;
		op_a_i = $random;
		operator_i = $random;
		mult_en_i = $random;
		signed_mode_i = $random;
		alu_adder_i = $random;
		equal_to_zero = $random;
		op_b_i = $random;
		#26;
	end

endmodule

example/ibex_multdiv_slow/ibex_multdiv_slow.vcd
$date
	Tue Mar 10 22:09:27 2020
$end
$version
	Icarus Verilog
$end
$timescale
	1ps
$end
$scope module ibex_multdiv_slow_bench $end
$scope module ibex_multdiv_slow_ $end
$var wire 34 ! alu_adder_ext_i [33:0] $end
$var wire 32 " alu_adder_i [31:0] $end
$var wire 1 # clk_i $end
$var wire 1 $ div_change_sign $end
$var wire 1 % div_en_i $end
$var wire 1 & equal_to_zero $end
$var wire 1 ' mult_en_i $end
$var wire 32 ( op_a_i [31:0] $end
$var wire 32 ) op_b_i [31:0] $end
$var wire 33 * op_remainder [32:0] $end
$var wire 2 + operator_i [1:0] $end
$var wire 1 , rem_change_sign $end
$var wire 1 - rst_ni $end
$var wire 1 . sign_a $end
$var wire 1 / sign_b $end
$var wire 2 0 signed_mode_i [1:0] $end
$var wire 1 1 valid_o $end
$var wire 33 2 res_adder_l [32:0] $end
$var wire 33 3 res_adder_h [32:0] $end
$var wire 33 4 op_b_ext [32:0] $end
$var wire 33 5 op_a_ext [32:0] $end
$var wire 33 6 op_a_bw_pp [32:0] $end
$var wire 33 7 op_a_bw_last_pp [32:0] $end
$var wire 33 8 one_shift [32:0] $end
$var wire 33 9 next_reminder [32:0] $end
$var wire 33 : next_quotient [32:0] $end
$var wire 5 ; multdiv_state_m1 [4:0] $end
$var wire 1 < is_greater_equal $end
$var wire 32 = b_0 [31:0] $end
$var reg 33 > accum_window_d [32:0] $end
$var reg 33 ? accum_window_q [32:0] $end
$var reg 33 @ alu_operand_a_o [32:0] $end
$var reg 33 A alu_operand_b_o [32:0] $end
$var reg 3 B md_state_d [2:0] $end
$var reg 3 C md_state_q [2:0] $end
$var reg 32 D multdiv_result_o [31:0] $end
$var reg 5 E multdiv_state_d [4:0] $end
$var reg 5 F multdiv_state_q [4:0] $end
$var reg 33 G op_a_shift_d [32:0] $end
$var reg 33 H op_a_shift_q [32:0] $end
$var reg 33 I op_b_shift_d [32:0] $end
$var reg 33 J op_b_shift_q [32:0] $end
$var reg 32 K op_numerator_d [31:0] $end
$var reg 32 L op_numerator_q [31:0] $end
$scope begin proc_multdiv_state_q $end
$upscope $end
$upscope $end
$upscope $end
$enddefinitions $end
#0
$dumpvars
b0 L
b0 K
b0 J
b0 I
b0 H
b0 G
b0 F
b0 E
bx D
b0 C
b0 B
bx1 A
b1 @
b0 ?
b0 >
b0 =
x<
b11111 ;
b0x :
bx 9
b1 8
b11111111111111111111111111111111 7
b100000000000000000000000000000000 6
bx 5
bx 4
bx 3
bx 2
01
bx 0
x/
x.
0-
x,
bx +
b0 *
bx )
bx (
x'
x&
x%
x$
1#
bx "
bx !
$end
#24000
b1 :
1<
1$
0/
1,
1.
b1001000010101001101010010010 9
b11111 E
b1 B
b110000100100001001101011000001001 >
b111111110000110000011100111111101 A
b0 D
b1 @
b10010000101010011010100100100 2
b1001000010101001101010010010 3
b111100111110001100000001 4
b111100111110001100000001 )
0&
b10110010110000101000010001100101 "
b1 0
1'
b11 +
b110000100100001001101011000001001 5
b10000100100001001101011000001001 (
1%
b10010000101010011010100100100 !
#25000
0#
#26000
1-
#50000
b10000000000000000000000000000000 :
b11110110111101100101001111101101 A
b10000100100001001101011000001001 D
b1 @
b10 B
b10110010110000101000010001100101 K
b1 C
b110000100100001001101011000001001 *
b110000100100001001101011000001001 ?
b10000000000000000000000000000000 8
b11110 ;
b11111 F
1#
#74000
0$
0,
0.
b11011010111110011010000110 9
b1 B
b0 K
b100000000000000000000000000000000 A
b110110101111100110100001101 D
b110000100100001001101011000001001 @
b110110101111100110100001101 2
b11011010111110011010000110 3
b11010101000100111101001010101010 4
b11010101000100111101001010101010 )
1&
b11100011001101110010010011000110 "
0'
b1 +
b11110100011011100110100111101 5
b11110100011011100110100111101 (
0%
b110110101111100110100001101 !
#75000
0#
#100000
1#
#124000
b111001010101111111101111110010 9
b10 B
b10001001001100101101011000010010 K
b11101101100110100101001111011011 A
b1 @
b10000100100001001101011000001001 D
b1110010101011111111011111100101 2
b111001010101111111101111110010 3
b101110010110000100100101011100 4
b101110010110000100100101011100 )
b11110100000000000111101011101000 "
b10 0
b11 +
b10001001001100101101011000010010 5
b10001001001100101101011000010010 (
1%
b1110010101011111111011111100101 !
#125000
0#
#150000
b110100011010011110110110101000111 A
b1 @
b11 B
b101110010110000100100101011100 I
b1 >
b10 C
b10001001001100101101011000010010 L
1#
#174000
b111101111010001110001010001011110 9
b1100010011001100110011011000101 A
b1 @
b11 B
b11001110110011001100110010011101 I
b1 >
b111011110100011100010100010111101 2
b111101111010001110001010001011110 3
b11001110110011001100110010011101 4
b11001110110011001100110010011101 )
0&
b10000011001000010000100100000 "
b0 0
b10110010101001110010011001100101 5
b10110010101001110010011001100101 (
b1111011110100011100010100010111101 !
#175000
0#
#200000
b1 9
b0 :
0<
b11111111111111111111111111111111 =
b0 G
b10 >
b11110 E
b11 @
b1 D
b11 C
b11001110110011001100110010011101 J
b1 *
b1 ?
1#
#224000
1$
1,
1.
b11 @
b10 >
b11110 E
b111001011001000000011111010010110 2
b111100101100100000001111101001011 3
b1110111111111110100100011101 4
b1110111111111110100100011101 )
b10000001000101110100101000000010 "
b1 0
1'
b110000110101111000011100000001101 5
b10000110101111000011100000001101 (
b1111001011001000000011111010010110 !
#225000
0#
#250000
b100 >
b10 D
b101 @
b10 9
b11101 E
b10 *
b10 ?
b1000000000000000000000000000000 8
b11101 ;
b11110 F
1#
#274000
1/
0,
0.
b101 @
b100 >
b11101 E
b111100111110001010111001011001111 2
b111110011111000101011100101100111 3
b111101100010010110011010011011000 4
b11101100010010110011010011011000 )
1&
b1000101001011100110000110001010 "
b10 0
0'
b10 +
b101000010010110010100001010 5
b101000010010110010100001010 (
b1111100111110001010111001011001111 !
#275000
0#
#300000
b1000 >
b100 D
b1001 @
b100 9
b11100 E
b100 *
b100 ?
b100000000000000000000000000000 8
b11100 ;
b11101 F
1#
#324000
b1001 @
b1000 >
b11100 E
b111100001000001111001101111000 2
b11110000100000111100110111100 3
b110000101110101111001101000001011 4
b10000101110101111001101000001011 )
0&
b11011110011101010000001010111100 "
b1110101110001010000110111101011 5
b1110101110001010000110111101011 (
b111100001000001111001101111000 !
#325000
0#
#350000
b1000 D
b10001 @
b1000 9
b10001 >
b11011 E
b1000 *
b1000 ?
b10000000000000000000000000000 8
b11011 ;
b11100 F
1#
